Workbook

Sheet Cleaned_sheet
A1: Transaction ID | B1: Date | C1: Type | D1: Category | E1: Department | F1: Description | G1: Amount (USD) | H1: Currency | I1: Rep / Vendor | J1: Month | K1: Quarter | L1: Notes | N1: Department_Clean | O1: Date_Clean | P1: Raw Variant | Q1: Clean Name | R1: Month_Clean | S1: Quarter_Clean | T1: Amount_Clean_USD
A2: TXN-1003 | B2: 09-01-2024 | C2: Revenue | D2: Subscription | E2: Sales Dept | F2: Subscription - Pinnacle Systems | G2: 68037.03 | H2: USD | I2: James Okafor | J2: Jan | K2: Q1 | N2: =IFERROR(VLOOKUP(TRIM(E2),$P$2:$Q$23,2,FALSE),"UNMAPPED - CHECK") -> Sales | O2: =IFERROR(__xludf.DUMMYFUNCTION("IFERROR( IF(LEN(TRIM(B2))=6, DATE(2000+VALUE(RIGHT(TRIM(B2),2)),MATCH(LEFT(TRIM(B2),3),{""Jan"",""Feb"",""Mar"",""Apr"",""May"",""Jun"",""Jul"",""Aug"",""Sep"",""Oct"",""Nov"",""Dec""},0),15), IF(REGEXMATCH(TRIM(B2),""^\d{2}[/-]\d{2}[/-]\d{4}$""),"&" DATE(VALUE(RIGHT(TRIM(B2),4)),VALUE(MID(TRIM(B2),4,2)),VALUE(LEFT(TRIM(B2),2))), DATEVALUE(TRIM(B2)))), ""CHECK"")"),45300.0) -> 45300 | P2: CLOUD | Q2: Cloud Infrastructure | R2: =IF(O2="CHECK","CHECK",TEXT(O2,"mmm")) -> Jan | S2: =IF(O2="CHECK","CHECK","Q"&INT((MONTH(O2)-1)/3)+1) -> Q1 | T2: =IFERROR(IF(G2="see notes",IF(ISNUMBER(VALUE(L2)),VALUE(L2),0),IF(G2="",0,IF(H2="GBP",VALUE(G2)*1.27,IF(AND(ISNUMBER(VALUE(G2)),F2="Revenue",VALUE(G2)<0),ABS(VALUE(G2)),IF(ISNUMBER(VALUE(G2)),VALUE(G2),0))))),0) -> 68037.03
A3: TXN-1519 | B3: 2024-12-25 | C3: Expense | D3: Cloud Infrastructure | E3: cloud infra | F3: Contractor - Delta Airlines | G3: 39375.28 | H3: USD | I3: Delta Airlines | J3: Dec | K3: Q4 | N3: =IFERROR(VLOOKUP(TRIM(E3),$P$2:$Q$23,2,FALSE),"UNMAPPED - CHECK") -> Cloud Infrastructure | O3: =IFERROR(__xludf.DUMMYFUNCTION("IFERROR( IF(LEN(TRIM(B3))=6, DATE(2000+VALUE(RIGHT(TRIM(B3),2)),MATCH(LEFT(TRIM(B3),3),{""Jan"",""Feb"",""Mar"",""Apr"",""May"",""Jun"",""Jul"",""Aug"",""Sep"",""Oct"",""Nov"",""Dec""},0),15), IF(REGEXMATCH(TRIM(B3),""^\d{2}[/-]\d{2}[/-]\d{4}$""),"&" DATE(VALUE(RIGHT(TRIM(B3),4)),VALUE(MID(TRIM(B3),4,2)),VALUE(LEFT(TRIM(B3),2))), DATEVALUE(TRIM(B3)))), ""CHECK"")"),45651.0) -> 45651 | P3: Cloud Infrastructure | Q3: Cloud Infrastructure | R3: =IF(O3="CHECK","CHECK",TEXT(O3,"mmm")) -> Dec | S3: =IF(O3="CHECK","CHECK","Q"&INT((MONTH(O3)-1)/3)+1) -> Q4 | T3: =IFERROR(IF(G3="see notes",IF(ISNUMBER(VALUE(L3)),VALUE(L3),0),IF(G3="",0,IF(H3="GBP",VALUE(G3)*1.27,IF(AND(ISNUMBER(VALUE(G3)),F3="Revenue",VALUE(G3)<0),ABS(VALUE(G3)),IF(ISNUMBER(VALUE(G3)),VALUE(G3),0))))),0) -> 39375.28
A4: TXN-1083 | B4: 03/20/2024 | C4: Revenue | D4: Subscription | E4: Sales Dept | F4: Subscription - Redwood Partners | G4: 251866.75 | H4: USD | I4: Aisha Rahman | J4: Mar | K4: Q1 | N4: =IFERROR(VLOOKUP(TRIM(E4),$P$2:$Q$23,2,FALSE),"UNMAPPED - CHECK") -> Sales | O4: =IFERROR(__xludf.DUMMYFUNCTION("IFERROR( IF(LEN(TRIM(B4))=6, DATE(2000+VALUE(RIGHT(TRIM(B4),2)),MATCH(LEFT(TRIM(B4),3),{""Jan"",""Feb"",""Mar"",""Apr"",""May"",""Jun"",""Jul"",""Aug"",""Sep"",""Oct"",""Nov"",""Dec""},0),15), IF(REGEXMATCH(TRIM(B4),""^\d{2}[/-]\d{2}[/-]\d{4}$""),"&" DATE(VALUE(RIGHT(TRIM(B4),4)),VALUE(MID(TRIM(B4),4,2)),VALUE(LEFT(TRIM(B4),2))), DATEVALUE(TRIM(B4)))), ""CHECK"")"),45872.0) -> 45872 | P4: cloud infra | Q4: Cloud Infrastructure | R4: =IF(O4="CHECK","CHECK",TEXT(O4,"mmm")) -> Aug | S4: =IF(O4="CHECK","CHECK","Q"&INT((MONTH(O4)-1)/3)+1) -> Q3 | T4: =IFERROR(IF(G4="see notes",IF(ISNUMBER(VALUE(L4)),VALUE(L4),0),IF(G4="",0,IF(H4="GBP",VALUE(G4)*1.27,IF(AND(ISNUMBER(VALUE(G4)),F4="Revenue",VALUE(G4)<0),ABS(VALUE(G4)),IF(ISNUMBER(VALUE(G4)),VALUE(G4),0))))),0) -> 251866.75
A5: TXN-1428 | B5: October 22, 2024 | C5: Expense | D5: Cloud Infrastructure | E5: CLOUD | F5: Salary - Accenture | G5: 22219.83 | H5: USD | I5: Accenture | J5: Oct | K5: Q4 | N5: =IFERROR(VLOOKUP(TRIM(E5),$P$2:$Q$23,2,FALSE),"UNMAPPED - CHECK") -> Cloud Infrastructure | O5: =IFERROR(__xludf.DUMMYFUNCTION("IFERROR( IF(LEN(TRIM(B5))=6, DATE(2000+VALUE(RIGHT(TRIM(B5),2)),MATCH(LEFT(TRIM(B5),3),{""Jan"",""Feb"",""Mar"",""Apr"",""May"",""Jun"",""Jul"",""Aug"",""Sep"",""Oct"",""Nov"",""Dec""},0),15), IF(REGEXMATCH(TRIM(B5),""^\d{2}[/-]\d{2}[/-]\d{4}$""),"&" DATE(VALUE(RIGHT(TRIM(B5),4)),VALUE(MID(TRIM(B5),4,2)),VALUE(LEFT(TRIM(B5),2))), DATEVALUE(TRIM(B5)))), ""CHECK"")"),45587.0) -> 45587 | P5: CS | Q5: Customer Success | R5: =IF(O5="CHECK","CHECK",TEXT(O5,"mmm")) -> Oct | S5: =IF(O5="CHECK","CHECK","Q"&INT((MONTH(O5)-1)/3)+1) -> Q4 | T5: =IFERROR(IF(G5="see notes",IF(ISNUMBER(VALUE(L5)),VALUE(L5),0),IF(G5="",0,IF(H5="GBP",VALUE(G5)*1.27,IF(AND(ISNUMBER(VALUE(G5)),F5="Revenue",VALUE(G5)<0),ABS(VALUE(G5)),IF(ISNUMBER(VALUE(G5)),VALUE(G5),0))))),0) -> 22219.83
A6: TXN-1276 | B6: 03-07-2024 | C6: Expense | D6: Marketing | E6: marketing | F6: Salary - Hilton Hotels | G6: 54150.77 | H6: USD | I6: Hilton Hotels | J6: Jul | K6: Q3 | N6: =IFERROR(VLOOKUP(TRIM(E6),$P$2:$Q$23,2,FALSE),"UNMAPPED - CHECK") -> Marketing | O6: =IFERROR(__xludf.DUMMYFUNCTION("IFERROR( IF(LEN(TRIM(B6))=6, DATE(2000+VALUE(RIGHT(TRIM(B6),2)),MATCH(LEFT(TRIM(B6),3),{""Jan"",""Feb"",""Mar"",""Apr"",""May"",""Jun"",""Jul"",""Aug"",""Sep"",""Oct"",""Nov"",""Dec""},0),15), IF(REGEXMATCH(TRIM(B6),""^\d{2}[/-]\d{2}[/-]\d{4}$""),"&" DATE(VALUE(RIGHT(TRIM(B6),4)),VALUE(MID(TRIM(B6),4,2)),VALUE(LEFT(TRIM(B6),2))), DATEVALUE(TRIM(B6)))), ""CHECK"")"),45476.0) -> 45476 | P6: Customer Success | Q6: Customer Success | R6: =IF(O6="CHECK","CHECK",TEXT(O6,"mmm")) -> Jul | S6: =IF(O6="CHECK","CHECK","Q"&INT((MONTH(O6)-1)/3)+1) -> Q3 | T6: =IFERROR(IF(G6="see notes",IF(ISNUMBER(VALUE(L6)),VALUE(L6),0),IF(G6="",0,IF(H6="GBP",VALUE(G6)*1.27,IF(AND(ISNUMBER(VALUE(G6)),F6="Revenue",VALUE(G6)<0),ABS(VALUE(G6)),IF(ISNUMBER(VALUE(G6)),VALUE(G6),0))))),0) -> 54150.77
A7: TXN-1129 | B7: April 14, 2024 | C7: Revenue | D7: Licensing | E7: sales | F7: Licensing - Redwood Partners | G7: 6708.47 | H7: USD | I7: Priya Nair | J7: Apr | K7: Q2 | N7: =IFERROR(VLOOKUP(TRIM(E7),$P$2:$Q$23,2,FALSE),"UNMAPPED - CHECK") -> Sales | O7: =IFERROR(__xludf.DUMMYFUNCTION("IFERROR( IF(LEN(TRIM(B7))=6, DATE(2000+VALUE(RIGHT(TRIM(B7),2)),MATCH(LEFT(TRIM(B7),3),{""Jan"",""Feb"",""Mar"",""Apr"",""May"",""Jun"",""Jul"",""Aug"",""Sep"",""Oct"",""Nov"",""Dec""},0),15), IF(REGEXMATCH(TRIM(B7),""^\d{2}[/-]\d{2}[/-]\d{4}$""),"&" DATE(VALUE(RIGHT(TRIM(B7),4)),VALUE(MID(TRIM(B7),4,2)),VALUE(LEFT(TRIM(B7),2))), DATEVALUE(TRIM(B7)))), ""CHECK"")"),45396.0) -> 45396 | P7: Customer Suc. | Q7: Customer Success | R7: =IF(O7="CHECK","CHECK",TEXT(O7,"mmm")) -> Apr | S7: =IF(O7="CHECK","CHECK","Q"&INT((MONTH(O7)-1)/3)+1) -> Q2 | T7: =IFERROR(IF(G7="see notes",IF(ISNUMBER(VALUE(L7)),VALUE(L7),0),IF(G7="",0,IF(H7="GBP",VALUE(G7)*1.27,IF(AND(ISNUMBER(VALUE(G7)),F7="Revenue",VALUE(G7)<0),ABS(VALUE(G7)),IF(ISNUMBER(VALUE(G7)),VALUE(G7),0))))),0) -> 6708.47
A8: TXN-1348 | B8: 2024-09-15 | C8: Revenue | D8: Subscription | E8: sales | F8: Subscription - Apex Retail | G8: 149903.37 | H8: USD | I8: Kwame Asante | J8: Sep | K8: Q3 | N8: =IFERROR(VLOOKUP(TRIM(E8),$P$2:$Q$23,2,FALSE),"UNMAPPED - CHECK") -> Sales | O8: =IFERROR(__xludf.DUMMYFUNCTION("IFERROR( IF(LEN(TRIM(B8))=6, DATE(2000+VALUE(RIGHT(TRIM(B8),2)),MATCH(LEFT(TRIM(B8),3),{""Jan"",""Feb"",""Mar"",""Apr"",""May"",""Jun"",""Jul"",""Aug"",""Sep"",""Oct"",""Nov"",""Dec""},0),15), IF(REGEXMATCH(TRIM(B8),""^\d{2}[/-]\d{2}[/-]\d{4}$""),"&" DATE(VALUE(RIGHT(TRIM(B8),4)),VALUE(MID(TRIM(B8),4,2)),VALUE(LEFT(TRIM(B8),2))), DATEVALUE(TRIM(B8)))), ""CHECK"")"),45550.0) -> 45550 | P8: Cust Success | Q8: Customer Success | R8: =IF(O8="CHECK","CHECK",TEXT(O8,"mmm")) -> Sep | S8: =IF(O8="CHECK","CHECK","Q"&INT((MONTH(O8)-1)/3)+1) -> Q3 | T8: =IFERROR(IF(G8="see notes",IF(ISNUMBER(VALUE(L8)),VALUE(L8),0),IF(G8="",0,IF(H8="GBP",VALUE(G8)*1.27,IF(AND(ISNUMBER(VALUE(G8)),F8="Revenue",VALUE(G8)<0),ABS(VALUE(G8)),IF(ISNUMBER(VALUE(G8)),VALUE(G8),0))))),0) -> 149903.37
A9: TXN-1295 | B9: 07/21/2024 | C9: Expense | D9: Cloud Infrastructure | E9: Cloud | F9: Legal - Salesforce | G9: 10013.89 | H9: GBP | I9: Salesforce | J9: Jul | K9: Q3 | N9: =IFERROR(VLOOKUP(TRIM(E9),$P$2:$Q$23,2,FALSE),"UNMAPPED - CHECK") -> Cloud Infrastructure | O9: =IFERROR(__xludf.DUMMYFUNCTION("IFERROR( IF(LEN(TRIM(B9))=6, DATE(2000+VALUE(RIGHT(TRIM(B9),2)),MATCH(LEFT(TRIM(B9),3),{""Jan"",""Feb"",""Mar"",""Apr"",""May"",""Jun"",""Jul"",""Aug"",""Sep"",""Oct"",""Nov"",""Dec""},0),15), IF(REGEXMATCH(TRIM(B9),""^\d{2}[/-]\d{2}[/-]\d{4}$""),"&" DATE(VALUE(RIGHT(TRIM(B9),4)),VALUE(MID(TRIM(B9),4,2)),VALUE(LEFT(TRIM(B9),2))), DATEVALUE(TRIM(B9)))), ""CHECK"")"),45907.0) -> 45907 | P9: Eng | Q9: Engineering | R9: =IF(O9="CHECK","CHECK",TEXT(O9,"mmm")) -> Sep | S9: =IF(O9="CHECK","CHECK","Q"&INT((MONTH(O9)-1)/3)+1) -> Q3 | T9: =IFERROR(IF(G9="see notes",IF(ISNUMBER(VALUE(L9)),VALUE(L9),0),IF(G9="",0,IF(H9="GBP",VALUE(G9)*1.27,IF(AND(ISNUMBER(VALUE(G9)),F9="Revenue",VALUE(G9)<0),ABS(VALUE(G9)),IF(ISNUMBER(VALUE(G9)),VALUE(G9),0))))),0) -> 12717.64
A10: TXN-1170 | B10: 10-05-2024 | C10: Revenue | D10: Professional Services | E10: Sales Dept | F10: Professional Services - Altura Health | G10: 21411.91 | H10: USD | I10: Kwame Asante | J10: May | K10: Q2 | N10: =IFERROR(VLOOKUP(TRIM(E10),$P$2:$Q$23,2,FALSE),"UNMAPPED - CHECK") -> Sales | O10: =IFERROR(__xludf.DUMMYFUNCTION("IFERROR( IF(LEN(TRIM(B10))=6, DATE(2000+VALUE(RIGHT(TRIM(B10),2)),MATCH(LEFT(TRIM(B10),3),{""Jan"",""Feb"",""Mar"",""Apr"",""May"",""Jun"",""Jul"",""Aug"",""Sep"",""Oct"",""Nov"",""Dec""},0),15), IF(REGEXMATCH(TRIM(B10),""^\d{2}[/-]\d{2}[/-]\d{4}$"&"""), DATE(VALUE(RIGHT(TRIM(B10),4)),VALUE(MID(TRIM(B10),4,2)),VALUE(LEFT(TRIM(B10),2))), DATEVALUE(TRIM(B10)))), ""CHECK"")"),45422.0) -> 45422 | P10: Engineering | Q10: Engineering | R10: =IF(O10="CHECK","CHECK",TEXT(O10,"mmm")) -> May | S10: =IF(O10="CHECK","CHECK","Q"&INT((MONTH(O10)-1)/3)+1) -> Q2 | T10: =IFERROR(IF(G10="see notes",IF(ISNUMBER(VALUE(L10)),VALUE(L10),0),IF(G10="",0,IF(H10="GBP",VALUE(G10)*1.27,IF(AND(ISNUMBER(VALUE(G10)),F10="Revenue",VALUE(G10)<0),ABS(VALUE(G10)),IF(ISNUMBER(VALUE(G10)),VALUE(G10),0))))),0) -> 21411.91
A11: TXN-1379 | B11: Sep-24 | C11: Expense | D11: G&A | E11: G and A | F11: Legal - WeWork | G11: 9918.62 | H11: USD | I11: WeWork | J11: Sep | K11: Q3 | N11: =IFERROR(VLOOKUP(TRIM(E11),$P$2:$Q$23,2,FALSE),"UNMAPPED - CHECK") -> G&A | O11: =IFERROR(__xludf.DUMMYFUNCTION("IFERROR( IF(LEN(TRIM(B11))=6, DATE(2000+VALUE(RIGHT(TRIM(B11),2)),MATCH(LEFT(TRIM(B11),3),{""Jan"",""Feb"",""Mar"",""Apr"",""May"",""Jun"",""Jul"",""Aug"",""Sep"",""Oct"",""Nov"",""Dec""},0),15), IF(REGEXMATCH(TRIM(B11),""^\d{2}[/-]\d{2}[/-]\d{4}$"&"""), DATE(VALUE(RIGHT(TRIM(B11),4)),VALUE(MID(TRIM(B11),4,2)),VALUE(LEFT(TRIM(B11),2))), DATEVALUE(TRIM(B11)))), ""CHECK"")"),45550.0) -> 45550 | P11: R&D | Q11: Engineering | R11: =IF(O11="CHECK","CHECK",TEXT(O11,"mmm")) -> Sep | S11: =IF(O11="CHECK","CHECK","Q"&INT((MONTH(O11)-1)/3)+1) -> Q3 | T11: =IFERROR(IF(G11="see notes",IF(ISNUMBER(VALUE(L11)),VALUE(L11),0),IF(G11="",0,IF(H11="GBP",VALUE(G11)*1.27,IF(AND(ISNUMBER(VALUE(G11)),F11="Revenue",VALUE(G11)<0),ABS(VALUE(G11)),IF(ISNUMBER(VALUE(G11)),VALUE(G11),0))))),0) -> 9918.62
A12: TXN-1131 | B12: 06/04/2024 | C12: Revenue | D12: Licensing | E12: SALES | F12: Licensing - BlueSky Logistics | G12: 6750.78 | H12: USD | I12: Kwame Asante | J12: Apr | K12: Q2 | N12: =IFERROR(VLOOKUP(TRIM(E12),$P$2:$Q$23,2,FALSE),"UNMAPPED - CHECK") -> Sales | O12: =IFERROR(__xludf.DUMMYFUNCTION("IFERROR( IF(LEN(TRIM(B12))=6, DATE(2000+VALUE(RIGHT(TRIM(B12),2)),MATCH(LEFT(TRIM(B12),3),{""Jan"",""Feb"",""Mar"",""Apr"",""May"",""Jun"",""Jul"",""Aug"",""Sep"",""Oct"",""Nov"",""Dec""},0),15), IF(REGEXMATCH(TRIM(B12),""^\d{2}[/-]\d{2}[/-]\d{4}$"&"""), DATE(VALUE(RIGHT(TRIM(B12),4)),VALUE(MID(TRIM(B12),4,2)),VALUE(LEFT(TRIM(B12),2))), DATEVALUE(TRIM(B12)))), ""CHECK"")"),45388.0) -> 45388 | P12: engineering | Q12: Engineering | R12: =IF(O12="CHECK","CHECK",TEXT(O12,"mmm")) -> Apr | S12: =IF(O12="CHECK","CHECK","Q"&INT((MONTH(O12)-1)/3)+1) -> Q2 | T12: =IFERROR(IF(G12="see notes",IF(ISNUMBER(VALUE(L12)),VALUE(L12),0),IF(G12="",0,IF(H12="GBP",VALUE(G12)*1.27,IF(AND(ISNUMBER(VALUE(G12)),F12="Revenue",VALUE(G12)<0),ABS(VALUE(G12)),IF(ISNUMBER(VALUE(G12)),VALUE(G12),0))))),0) -> 6750.78
A13: TXN-1117 | B13: Mar-24 | C13: Expense | D13: Cloud Infrastructure | E13: Cloud | F13: Recruiting - Randstad | G13: 16812.38 | H13: USD | I13: Randstad | J13: Mar | K13: Q1 | N13: =IFERROR(VLOOKUP(TRIM(E13),$P$2:$Q$23,2,FALSE),"UNMAPPED - CHECK") -> Cloud Infrastructure | O13: =IFERROR(__xludf.DUMMYFUNCTION("IFERROR( IF(LEN(TRIM(B13))=6, DATE(2000+VALUE(RIGHT(TRIM(B13),2)),MATCH(LEFT(TRIM(B13),3),{""Jan"",""Feb"",""Mar"",""Apr"",""May"",""Jun"",""Jul"",""Aug"",""Sep"",""Oct"",""Nov"",""Dec""},0),15), IF(REGEXMATCH(TRIM(B13),""^\d{2}[/-]\d{2}[/-]\d{4}$"&"""), DATE(VALUE(RIGHT(TRIM(B13),4)),VALUE(MID(TRIM(B13),4,2)),VALUE(LEFT(TRIM(B13),2))), DATEVALUE(TRIM(B13)))), ""CHECK"")"),45366.0) -> 45366 | P13: G & A | Q13: G&A | R13: =IF(O13="CHECK","CHECK",TEXT(O13,"mmm")) -> Mar | S13: =IF(O13="CHECK","CHECK","Q"&INT((MONTH(O13)-1)/3)+1) -> Q1 | T13: =IFERROR(IF(G13="see notes",IF(ISNUMBER(VALUE(L13)),VALUE(L13),0),IF(G13="",0,IF(H13="GBP",VALUE(G13)*1.27,IF(AND(ISNUMBER(VALUE(G13)),F13="Revenue",VALUE(G13)<0),ABS(VALUE(G13)),IF(ISNUMBER(VALUE(G13)),VALUE(G13),0))))),0) -> 16812.38
A14: TXN-1328 | B14: Aug-24 | C14: Expense | D14: Engineering | E14: Eng | F14: Salary - Delta Airlines | G14: 21612.23 | H14: USD | I14: Delta Airlines | J14: Aug | K14: Q3 | N14: =IFERROR(VLOOKUP(TRIM(E14),$P$2:$Q$23,2,FALSE),"UNMAPPED - CHECK") -> Engineering | O14: =IFERROR(__xludf.DUMMYFUNCTION("IFERROR( IF(LEN(TRIM(B14))=6, DATE(2000+VALUE(RIGHT(TRIM(B14),2)),MATCH(LEFT(TRIM(B14),3),{""Jan"",""Feb"",""Mar"",""Apr"",""May"",""Jun"",""Jul"",""Aug"",""Sep"",""Oct"",""Nov"",""Dec""},0),15), IF(REGEXMATCH(TRIM(B14),""^\d{2}[/-]\d{2}[/-]\d{4}$"&"""), DATE(VALUE(RIGHT(TRIM(B14),4)),VALUE(MID(TRIM(B14),4,2)),VALUE(LEFT(TRIM(B14),2))), DATEVALUE(TRIM(B14)))), ""CHECK"")"),45519.0) -> 45519 | P14: G&A | Q14: G&A | R14: =IF(O14="CHECK","CHECK",TEXT(O14,"mmm")) -> Aug | S14: =IF(O14="CHECK","CHECK","Q"&INT((MONTH(O14)-1)/3)+1) -> Q3 | T14: =IFERROR(IF(G14="see notes",IF(ISNUMBER(VALUE(L14)),VALUE(L14),0),IF(G14="",0,IF(H14="GBP",VALUE(G14)*1.27,IF(AND(ISNUMBER(VALUE(G14)),F14="Revenue",VALUE(G14)<0),ABS(VALUE(G14)),IF(ISNUMBER(VALUE(G14)),VALUE(G14),0))))),0) -> 21612.23
A15: TXN-1225 | B15: 2024-06-28 | C15: Expense | D15: Sales | E15: Sales | F15: Ad Spend - Hilton Hotels | G15: 10129.21 | H15: USD | I15: Hilton Hotels | J15: Jun | K15: Q2 | N15: =IFERROR(VLOOKUP(TRIM(E15),$P$2:$Q$23,2,FALSE),"UNMAPPED - CHECK") -> Sales | O15: =IFERROR(__xludf.DUMMYFUNCTION("IFERROR( IF(LEN(TRIM(B15))=6, DATE(2000+VALUE(RIGHT(TRIM(B15),2)),MATCH(LEFT(TRIM(B15),3),{""Jan"",""Feb"",""Mar"",""Apr"",""May"",""Jun"",""Jul"",""Aug"",""Sep"",""Oct"",""Nov"",""Dec""},0),15), IF(REGEXMATCH(TRIM(B15),""^\d{2}[/-]\d{2}[/-]\d{4}$"&"""), DATE(VALUE(RIGHT(TRIM(B15),4)),VALUE(MID(TRIM(B15),4,2)),VALUE(LEFT(TRIM(B15),2))), DATEVALUE(TRIM(B15)))), ""CHECK"")"),45471.0) -> 45471 | P15: General & Admin | Q15: G&A | R15: =IF(O15="CHECK","CHECK",TEXT(O15,"mmm")) -> Jun | S15: =IF(O15="CHECK","CHECK","Q"&INT((MONTH(O15)-1)/3)+1) -> Q2 | T15: =IFERROR(IF(G15="see notes",IF(ISNUMBER(VALUE(L15)),VALUE(L15),0),IF(G15="",0,IF(H15="GBP",VALUE(G15)*1.27,IF(AND(ISNUMBER(VALUE(G15)),F15="Revenue",VALUE(G15)<0),ABS(VALUE(G15)),IF(ISNUMBER(VALUE(G15)),VALUE(G15),0))))),0) -> 10129.21
A16: TXN-1369 | B16: 2024-09-05 | C16: Expense | D16: Engineering | E16: Eng | F16: Software License - Slack | G16: 32562.8 | H16: USD | I16: Slack | J16: Sep | K16: Q3 | N16: =IFERROR(VLOOKUP(TRIM(E16),$P$2:$Q$23,2,FALSE),"UNMAPPED - CHECK") -> Engineering | O16: =IFERROR(__xludf.DUMMYFUNCTION("IFERROR( IF(LEN(TRIM(B16))=6, DATE(2000+VALUE(RIGHT(TRIM(B16),2)),MATCH(LEFT(TRIM(B16),3),{""Jan"",""Feb"",""Mar"",""Apr"",""May"",""Jun"",""Jul"",""Aug"",""Sep"",""Oct"",""Nov"",""Dec""},0),15), IF(REGEXMATCH(TRIM(B16),""^\d{2}[/-]\d{2}[/-]\d{4}$"&"""), DATE(VALUE(RIGHT(TRIM(B16),4)),VALUE(MID(TRIM(B16),4,2)),VALUE(LEFT(TRIM(B16),2))), DATEVALUE(TRIM(B16)))), ""CHECK"")"),45540.0) -> 45540 | P16: G and A | Q16: G&A | R16: =IF(O16="CHECK","CHECK",TEXT(O16,"mmm")) -> Sep | S16: =IF(O16="CHECK","CHECK","Q"&INT((MONTH(O16)-1)/3)+1) -> Q3 | T16: =IFERROR(IF(G16="see notes",IF(ISNUMBER(VALUE(L16)),VALUE(L16),0),IF(G16="",0,IF(H16="GBP",VALUE(G16)*1.27,IF(AND(ISNUMBER(VALUE(G16)),F16="Revenue",VALUE(G16)<0),ABS(VALUE(G16)),IF(ISNUMBER(VALUE(G16)),VALUE(G16),0))))),0) -> 32562.8
A17: TXN-1272 | B17: 02-07-2024 | C17: Expense | D17: Sales | E17: Sales Dept | F17: AWS/Cloud - Delta Airlines | G17: 24078.44 | H17: USD | I17: Delta Airlines | J17: Jul | K17: Q3 | N17: =IFERROR(VLOOKUP(TRIM(E17),$P$2:$Q$23,2,FALSE),"UNMAPPED - CHECK") -> Sales | O17: =IFERROR(__xludf.DUMMYFUNCTION("IFERROR( IF(LEN(TRIM(B17))=6, DATE(2000+VALUE(RIGHT(TRIM(B17),2)),MATCH(LEFT(TRIM(B17),3),{""Jan"",""Feb"",""Mar"",""Apr"",""May"",""Jun"",""Jul"",""Aug"",""Sep"",""Oct"",""Nov"",""Dec""},0),15), IF(REGEXMATCH(TRIM(B17),""^\d{2}[/-]\d{2}[/-]\d{4}$"&"""), DATE(VALUE(RIGHT(TRIM(B17),4)),VALUE(MID(TRIM(B17),4,2)),VALUE(LEFT(TRIM(B17),2))), DATEVALUE(TRIM(B17)))), ""CHECK"")"),45475.0) -> 45475 | P17: marketing | Q17: Marketing | R17: =IF(O17="CHECK","CHECK",TEXT(O17,"mmm")) -> Jul | S17: =IF(O17="CHECK","CHECK","Q"&INT((MONTH(O17)-1)/3)+1) -> Q3 | T17: =IFERROR(IF(G17="see notes",IF(ISNUMBER(VALUE(L17)),VALUE(L17),0),IF(G17="",0,IF(H17="GBP",VALUE(G17)*1.27,IF(AND(ISNUMBER(VALUE(G17)),F17="Revenue",VALUE(G17)<0),ABS(VALUE(G17)),IF(ISNUMBER(VALUE(G17)),VALUE(G17),0))))),0) -> 24078.44
A18: TXN-1058 | B18: 02/20/2024 | C18: Expense | D18: Marketing | E18: Mktg | F18: Travel - Hilton Hotels | G18: 29097.3 | H18: USD | I18: Hilton Hotels | J18: Feb | K18: Q1 | N18: =IFERROR(VLOOKUP(TRIM(E18),$P$2:$Q$23,2,FALSE),"UNMAPPED - CHECK") -> Marketing | O18: =IFERROR(__xludf.DUMMYFUNCTION("IFERROR( IF(LEN(TRIM(B18))=6, DATE(2000+VALUE(RIGHT(TRIM(B18),2)),MATCH(LEFT(TRIM(B18),3),{""Jan"",""Feb"",""Mar"",""Apr"",""May"",""Jun"",""Jul"",""Aug"",""Sep"",""Oct"",""Nov"",""Dec""},0),15), IF(REGEXMATCH(TRIM(B18),""^\d{2}[/-]\d{2}[/-]\d{4}$"&"""), DATE(VALUE(RIGHT(TRIM(B18),4)),VALUE(MID(TRIM(B18),4,2)),VALUE(LEFT(TRIM(B18),2))), DATEVALUE(TRIM(B18)))), ""CHECK"")"),45871.0) -> 45871 | P18: Marketing | Q18: Marketing | R18: =IF(O18="CHECK","CHECK",TEXT(O18,"mmm")) -> Aug | S18: =IF(O18="CHECK","CHECK","Q"&INT((MONTH(O18)-1)/3)+1) -> Q3 | T18: =IFERROR(IF(G18="see notes",IF(ISNUMBER(VALUE(L18)),VALUE(L18),0),IF(G18="",0,IF(H18="GBP",VALUE(G18)*1.27,IF(AND(ISNUMBER(VALUE(G18)),F18="Revenue",VALUE(G18)<0),ABS(VALUE(G18)),IF(ISNUMBER(VALUE(G18)),VALUE(G18),0))))),0) -> 29097.3
A19: TXN-1001 | B19: Jan-24 | C19: Revenue | D19: Subscription | E19: Sales | F19: Subscription - Redwood Partners | G19: 559559.73 | H19: USD | I19: Sofia Andersen | J19: Jan | K19: Q1 | N19: =IFERROR(VLOOKUP(TRIM(E19),$P$2:$Q$23,2,FALSE),"UNMAPPED - CHECK") -> Sales | O19: =IFERROR(__xludf.DUMMYFUNCTION("IFERROR( IF(LEN(TRIM(B19))=6, DATE(2000+VALUE(RIGHT(TRIM(B19),2)),MATCH(LEFT(TRIM(B19),3),{""Jan"",""Feb"",""Mar"",""Apr"",""May"",""Jun"",""Jul"",""Aug"",""Sep"",""Oct"",""Nov"",""Dec""},0),15), IF(REGEXMATCH(TRIM(B19),""^\d{2}[/-]\d{2}[/-]\d{4}$"&"""), DATE(VALUE(RIGHT(TRIM(B19),4)),VALUE(MID(TRIM(B19),4,2)),VALUE(LEFT(TRIM(B19),2))), DATEVALUE(TRIM(B19)))), ""CHECK"")"),45306.0) -> 45306 | P19: Mktng | Q19: Marketing | R19: =IF(O19="CHECK","CHECK",TEXT(O19,"mmm")) -> Jan | S19: =IF(O19="CHECK","CHECK","Q"&INT((MONTH(O19)-1)/3)+1) -> Q1 | T19: =IFERROR(IF(G19="see notes",IF(ISNUMBER(VALUE(L19)),VALUE(L19),0),IF(G19="",0,IF(H19="GBP",VALUE(G19)*1.27,IF(AND(ISNUMBER(VALUE(G19)),F19="Revenue",VALUE(G19)<0),ABS(VALUE(G19)),IF(ISNUMBER(VALUE(G19)),VALUE(G19),0))))),0) -> 559559.73
A20: TXN-1256 | B20: 26-07-2024 | C20: Revenue | D20: Subscription | E20: sales | F20: Subscription - TechNova Ltd | G20: 105296.87 | H20: USD | I20: Tom Bradley | J20: Jul | K20: Q3 | N20: =IFERROR(VLOOKUP(TRIM(E20),$P$2:$Q$23,2,FALSE),"UNMAPPED - CHECK") -> Sales | O20: =IFERROR(__xludf.DUMMYFUNCTION("IFERROR( IF(LEN(TRIM(B20))=6, DATE(2000+VALUE(RIGHT(TRIM(B20),2)),MATCH(LEFT(TRIM(B20),3),{""Jan"",""Feb"",""Mar"",""Apr"",""May"",""Jun"",""Jul"",""Aug"",""Sep"",""Oct"",""Nov"",""Dec""},0),15), IF(REGEXMATCH(TRIM(B20),""^\d{2}[/-]\d{2}[/-]\d{4}$"&"""), DATE(VALUE(RIGHT(TRIM(B20),4)),VALUE(MID(TRIM(B20),4,2)),VALUE(LEFT(TRIM(B20),2))), DATEVALUE(TRIM(B20)))), ""CHECK"")"),45499.0) -> 45499 | P20: Mktg | Q20: Marketing | R20: =IF(O20="CHECK","CHECK",TEXT(O20,"mmm")) -> Jul | S20: =IF(O20="CHECK","CHECK","Q"&INT((MONTH(O20)-1)/3)+1) -> Q3 | T20: =IFERROR(IF(G20="see notes",IF(ISNUMBER(VALUE(L20)),VALUE(L20),0),IF(G20="",0,IF(H20="GBP",VALUE(G20)*1.27,IF(AND(ISNUMBER(VALUE(G20)),F20="Revenue",VALUE(G20)<0),ABS(VALUE(G20)),IF(ISNUMBER(VALUE(G20)),VALUE(G20),0))))),0) -> 105296.87
A21: TXN-1253 | B21: July 06, 2024 | C21: Revenue | D21: Subscription | E21: sales | F21: Subscription - Apex Retail | G21: 138733.49 | H21: USD | I21: Daniel Müller | J21: Jul | K21: Q3 | N21: =IFERROR(VLOOKUP(TRIM(E21),$P$2:$Q$23,2,FALSE),"UNMAPPED - CHECK") -> Sales | O21: =IFERROR(__xludf.DUMMYFUNCTION("IFERROR( IF(LEN(TRIM(B21))=6, DATE(2000+VALUE(RIGHT(TRIM(B21),2)),MATCH(LEFT(TRIM(B21),3),{""Jan"",""Feb"",""Mar"",""Apr"",""May"",""Jun"",""Jul"",""Aug"",""Sep"",""Oct"",""Nov"",""Dec""},0),15), IF(REGEXMATCH(TRIM(B21),""^\d{2}[/-]\d{2}[/-]\d{4}$"&"""), DATE(VALUE(RIGHT(TRIM(B21),4)),VALUE(MID(TRIM(B21),4,2)),VALUE(LEFT(TRIM(B21),2))), DATEVALUE(TRIM(B21)))), ""CHECK"")"),45479.0) -> 45479 | P21: sales | Q21: Sales | R21: =IF(O21="CHECK","CHECK",TEXT(O21,"mmm")) -> Jul | S21: =IF(O21="CHECK","CHECK","Q"&INT((MONTH(O21)-1)/3)+1) -> Q3 | T21: =IFERROR(IF(G21="see notes",IF(ISNUMBER(VALUE(L21)),VALUE(L21),0),IF(G21="",0,IF(H21="GBP",VALUE(G21)*1.27,IF(AND(ISNUMBER(VALUE(G21)),F21="Revenue",VALUE(G21)<0),ABS(VALUE(G21)),IF(ISNUMBER(VALUE(G21)),VALUE(G21),0))))),0) -> 138733.49
A22: TXN-1471 | B22: 23-11-2024 | C22: Expense | D22: Cloud Infrastructure | E22: cloud infra | F22: PR Agency - Zoom | G22: 33435.12 | H22: USD | I22: Zoom | J22: Nov | K22: Q4 | N22: =IFERROR(VLOOKUP(TRIM(E22),$P$2:$Q$23,2,FALSE),"UNMAPPED - CHECK") -> Cloud Infrastructure | O22: =IFERROR(__xludf.DUMMYFUNCTION("IFERROR( IF(LEN(TRIM(B22))=6, DATE(2000+VALUE(RIGHT(TRIM(B22),2)),MATCH(LEFT(TRIM(B22),3),{""Jan"",""Feb"",""Mar"",""Apr"",""May"",""Jun"",""Jul"",""Aug"",""Sep"",""Oct"",""Nov"",""Dec""},0),15), IF(REGEXMATCH(TRIM(B22),""^\d{2}[/-]\d{2}[/-]\d{4}$"&"""), DATE(VALUE(RIGHT(TRIM(B22),4)),VALUE(MID(TRIM(B22),4,2)),VALUE(LEFT(TRIM(B22),2))), DATEVALUE(TRIM(B22)))), ""CHECK"")"),45619.0) -> 45619 | P22: Sales Dept | Q22: Sales | R22: =IF(O22="CHECK","CHECK",TEXT(O22,"mmm")) -> Nov | S22: =IF(O22="CHECK","CHECK","Q"&INT((MONTH(O22)-1)/3)+1) -> Q4 | T22: =IFERROR(IF(G22="see notes",IF(ISNUMBER(VALUE(L22)),VALUE(L22),0),IF(G22="",0,IF(H22="GBP",VALUE(G22)*1.27,IF(AND(ISNUMBER(VALUE(G22)),F22="Revenue",VALUE(G22)<0),ABS(VALUE(G22)),IF(ISNUMBER(VALUE(G22)),VALUE(G22),0))))),0) -> 33435.12
A23: TXN-1385 | B23: 09/23/2024 | C23: Expense | D23: Cloud Infrastructure | E23: Cloud Infra | F23: Ad Spend - Linklaters LLP | G23: 18638.21 | H23: USD | I23: Linklaters LLP | J23: Sep | K23: Q3 | N23: =IFERROR(VLOOKUP(TRIM(E23),$P$2:$Q$23,2,FALSE),"UNMAPPED - CHECK") -> Cloud Infrastructure | O23: =IFERROR(__xludf.DUMMYFUNCTION("IFERROR( IF(LEN(TRIM(B23))=6, DATE(2000+VALUE(RIGHT(TRIM(B23),2)),MATCH(LEFT(TRIM(B23),3),{""Jan"",""Feb"",""Mar"",""Apr"",""May"",""Jun"",""Jul"",""Aug"",""Sep"",""Oct"",""Nov"",""Dec""},0),15), IF(REGEXMATCH(TRIM(B23),""^\d{2}[/-]\d{2}[/-]\d{4}$"&"""), DATE(VALUE(RIGHT(TRIM(B23),4)),VALUE(MID(TRIM(B23),4,2)),VALUE(LEFT(TRIM(B23),2))), DATEVALUE(TRIM(B23)))), ""CHECK"")"),45970.0) -> 45970 | P23: Sales | Q23: Sales | R23: =IF(O23="CHECK","CHECK",TEXT(O23,"mmm")) -> Nov | S23: =IF(O23="CHECK","CHECK","Q"&INT((MONTH(O23)-1)/3)+1) -> Q4 | T23: =IFERROR(IF(G23="see notes",IF(ISNUMBER(VALUE(L23)),VALUE(L23),0),IF(G23="",0,IF(H23="GBP",VALUE(G23)*1.27,IF(AND(ISNUMBER(VALUE(G23)),F23="Revenue",VALUE(G23)<0),ABS(VALUE(G23)),IF(ISNUMBER(VALUE(G23)),VALUE(G23),0))))),0) -> 18638.21
A24: TXN-1389 | B24: 10/10/2024 | C24: Revenue | D24: Subscription | E24: SALES | F24: Subscription - TechNova Ltd | G24: 90215.59 | H24: USD | I24: Daniel Müller | J24: Oct | K24: Q4 | N24: =IFERROR(VLOOKUP(TRIM(E24),$P$2:$Q$23,2,FALSE),"UNMAPPED - CHECK") -> Sales | O24: =IFERROR(__xludf.DUMMYFUNCTION("IFERROR( IF(LEN(TRIM(B24))=6, DATE(2000+VALUE(RIGHT(TRIM(B24),2)),MATCH(LEFT(TRIM(B24),3),{""Jan"",""Feb"",""Mar"",""Apr"",""May"",""Jun"",""Jul"",""Aug"",""Sep"",""Oct"",""Nov"",""Dec""},0),15), IF(REGEXMATCH(TRIM(B24),""^\d{2}[/-]\d{2}[/-]\d{4}$"&"""), DATE(VALUE(RIGHT(TRIM(B24),4)),VALUE(MID(TRIM(B24),4,2)),VALUE(LEFT(TRIM(B24),2))), DATEVALUE(TRIM(B24)))), ""CHECK"")"),45575.0) -> 45575 | R24: =IF(O24="CHECK","CHECK",TEXT(O24,"mmm")) -> Oct | S24: =IF(O24="CHECK","CHECK","Q"&INT((MONTH(O24)-1)/3)+1) -> Q4 | T24: =IFERROR(IF(G24="see notes",IF(ISNUMBER(VALUE(L24)),VALUE(L24),0),IF(G24="",0,IF(H24="GBP",VALUE(G24)*1.27,IF(AND(ISNUMBER(VALUE(G24)),F24="Revenue",VALUE(G24)<0),ABS(VALUE(G24)),IF(ISNUMBER(VALUE(G24)),VALUE(G24),0))))),0) -> 90215.59
A25: TXN-1402 | B25: October 13, 2024 | C25: Revenue | D25: Licensing | E25: Sales | F25: Licensing - Altura Health | G25: 7490.67 | H25: USD | I25: Tom Bradley | J25: Oct | K25: Q4 | N25: =IFERROR(VLOOKUP(TRIM(E25),$P$2:$Q$23,2,FALSE),"UNMAPPED - CHECK") -> Sales | O25: =IFERROR(__xludf.DUMMYFUNCTION("IFERROR( IF(LEN(TRIM(B25))=6, DATE(2000+VALUE(RIGHT(TRIM(B25),2)),MATCH(LEFT(TRIM(B25),3),{""Jan"",""Feb"",""Mar"",""Apr"",""May"",""Jun"",""Jul"",""Aug"",""Sep"",""Oct"",""Nov"",""Dec""},0),15), IF(REGEXMATCH(TRIM(B25),""^\d{2}[/-]\d{2}[/-]\d{4}$"&"""), DATE(VALUE(RIGHT(TRIM(B25),4)),VALUE(MID(TRIM(B25),4,2)),VALUE(LEFT(TRIM(B25),2))), DATEVALUE(TRIM(B25)))), ""CHECK"")"),45578.0) -> 45578 | R25: =IF(O25="CHECK","CHECK",TEXT(O25,"mmm")) -> Oct | S25: =IF(O25="CHECK","CHECK","Q"&INT((MONTH(O25)-1)/3)+1) -> Q4 | T25: =IFERROR(IF(G25="see notes",IF(ISNUMBER(VALUE(L25)),VALUE(L25),0),IF(G25="",0,IF(H25="GBP",VALUE(G25)*1.27,IF(AND(ISNUMBER(VALUE(G25)),F25="Revenue",VALUE(G25)<0),ABS(VALUE(G25)),IF(ISNUMBER(VALUE(G25)),VALUE(G25),0))))),0) -> 7490.67
A26: TXN-1279 | B26: July 26, 2024 | C26: Expense | D26: Engineering | E26: R&D | F26: Ad Spend - Zoom | G26: 26135.97 | H26: USD | I26: Zoom | J26: Jul | K26: Q3 | N26: =IFERROR(VLOOKUP(TRIM(E26),$P$2:$Q$23,2,FALSE),"UNMAPPED - CHECK") -> Engineering | O26: =IFERROR(__xludf.DUMMYFUNCTION("IFERROR( IF(LEN(TRIM(B26))=6, DATE(2000+VALUE(RIGHT(TRIM(B26),2)),MATCH(LEFT(TRIM(B26),3),{""Jan"",""Feb"",""Mar"",""Apr"",""May"",""Jun"",""Jul"",""Aug"",""Sep"",""Oct"",""Nov"",""Dec""},0),15), IF(REGEXMATCH(TRIM(B26),""^\d{2}[/-]\d{2}[/-]\d{4}$"&"""), DATE(VALUE(RIGHT(TRIM(B26),4)),VALUE(MID(TRIM(B26),4,2)),VALUE(LEFT(TRIM(B26),2))), DATEVALUE(TRIM(B26)))), ""CHECK"")"),45499.0) -> 45499 | R26: =IF(O26="CHECK","CHECK",TEXT(O26,"mmm")) -> Jul | S26: =IF(O26="CHECK","CHECK","Q"&INT((MONTH(O26)-1)/3)+1) -> Q3 | T26: =IFERROR(IF(G26="see notes",IF(ISNUMBER(VALUE(L26)),VALUE(L26),0),IF(G26="",0,IF(H26="GBP",VALUE(G26)*1.27,IF(AND(ISNUMBER(VALUE(G26)),F26="Revenue",VALUE(G26)<0),ABS(VALUE(G26)),IF(ISNUMBER(VALUE(G26)),VALUE(G26),0))))),0) -> 26135.97
A27: TXN-1199 | B27: May 14, 2024 | C27: Expense | D27: G&A | E27: G&A | F27: PR Agency - Delta Airlines | G27: 12105.45 | H27: USD | I27: Delta Airlines | J27: May | K27: Q2 | N27: =IFERROR(VLOOKUP(TRIM(E27),$P$2:$Q$23,2,FALSE),"UNMAPPED - CHECK") -> G&A | O27: =IFERROR(__xludf.DUMMYFUNCTION("IFERROR( IF(LEN(TRIM(B27))=6, DATE(2000+VALUE(RIGHT(TRIM(B27),2)),MATCH(LEFT(TRIM(B27),3),{""Jan"",""Feb"",""Mar"",""Apr"",""May"",""Jun"",""Jul"",""Aug"",""Sep"",""Oct"",""Nov"",""Dec""},0),15), IF(REGEXMATCH(TRIM(B27),""^\d{2}[/-]\d{2}[/-]\d{4}$"&"""), DATE(VALUE(RIGHT(TRIM(B27),4)),VALUE(MID(TRIM(B27),4,2)),VALUE(LEFT(TRIM(B27),2))), DATEVALUE(TRIM(B27)))), ""CHECK"")"),45426.0) -> 45426 | R27: =IF(O27="CHECK","CHECK",TEXT(O27,"mmm")) -> May | S27: =IF(O27="CHECK","CHECK","Q"&INT((MONTH(O27)-1)/3)+1) -> Q2 | T27: =IFERROR(IF(G27="see notes",IF(ISNUMBER(VALUE(L27)),VALUE(L27),0),IF(G27="",0,IF(H27="GBP",VALUE(G27)*1.27,IF(AND(ISNUMBER(VALUE(G27)),F27="Revenue",VALUE(G27)<0),ABS(VALUE(G27)),IF(ISNUMBER(VALUE(G27)),VALUE(G27),0))))),0) -> 12105.45
A28: TXN-1206 | B28: 2024-05-22 | C28: Expense | D28: Cloud Infrastructure | E28: Cloud Infrastructure | F28: Software License - Randstad | G28: 24138.1 | H28: USD | I28: Randstad | J28: May | K28: Q2 | N28: =IFERROR(VLOOKUP(TRIM(E28),$P$2:$Q$23,2,FALSE),"UNMAPPED - CHECK") -> Cloud Infrastructure | O28: =IFERROR(__xludf.DUMMYFUNCTION("IFERROR( IF(LEN(TRIM(B28))=6, DATE(2000+VALUE(RIGHT(TRIM(B28),2)),MATCH(LEFT(TRIM(B28),3),{""Jan"",""Feb"",""Mar"",""Apr"",""May"",""Jun"",""Jul"",""Aug"",""Sep"",""Oct"",""Nov"",""Dec""},0),15), IF(REGEXMATCH(TRIM(B28),""^\d{2}[/-]\d{2}[/-]\d{4}$"&"""), DATE(VALUE(RIGHT(TRIM(B28),4)),VALUE(MID(TRIM(B28),4,2)),VALUE(LEFT(TRIM(B28),2))), DATEVALUE(TRIM(B28)))), ""CHECK"")"),45434.0) -> 45434 | R28: =IF(O28="CHECK","CHECK",TEXT(O28,"mmm")) -> May | S28: =IF(O28="CHECK","CHECK","Q"&INT((MONTH(O28)-1)/3)+1) -> Q2 | T28: =IFERROR(IF(G28="see notes",IF(ISNUMBER(VALUE(L28)),VALUE(L28),0),IF(G28="",0,IF(H28="GBP",VALUE(G28)*1.27,IF(AND(ISNUMBER(VALUE(G28)),F28="Revenue",VALUE(G28)<0),ABS(VALUE(G28)),IF(ISNUMBER(VALUE(G28)),VALUE(G28),0))))),0) -> 24138.1
A29: TXN-1045 | B29: 2024-02-05 | C29: Revenue | D29: Professional Services | E29: SALES | F29: Professional Services - Synapse AI | G29: 20871.91 | H29: USD | I29: Kwame Asante | J29: Feb | K29: Q1 | N29: =IFERROR(VLOOKUP(TRIM(E29),$P$2:$Q$23,2,FALSE),"UNMAPPED - CHECK") -> Sales | O29: =IFERROR(__xludf.DUMMYFUNCTION("IFERROR( IF(LEN(TRIM(B29))=6, DATE(2000+VALUE(RIGHT(TRIM(B29),2)),MATCH(LEFT(TRIM(B29),3),{""Jan"",""Feb"",""Mar"",""Apr"",""May"",""Jun"",""Jul"",""Aug"",""Sep"",""Oct"",""Nov"",""Dec""},0),15), IF(REGEXMATCH(TRIM(B29),""^\d{2}[/-]\d{2}[/-]\d{4}$"&"""), DATE(VALUE(RIGHT(TRIM(B29),4)),VALUE(MID(TRIM(B29),4,2)),VALUE(LEFT(TRIM(B29),2))), DATEVALUE(TRIM(B29)))), ""CHECK"")"),45327.0) -> 45327 | R29: =IF(O29="CHECK","CHECK",TEXT(O29,"mmm")) -> Feb | S29: =IF(O29="CHECK","CHECK","Q"&INT((MONTH(O29)-1)/3)+1) -> Q1 | T29: =IFERROR(IF(G29="see notes",IF(ISNUMBER(VALUE(L29)),VALUE(L29),0),IF(G29="",0,IF(H29="GBP",VALUE(G29)*1.27,IF(AND(ISNUMBER(VALUE(G29)),F29="Revenue",VALUE(G29)<0),ABS(VALUE(G29)),IF(ISNUMBER(VALUE(G29)),VALUE(G29),0))))),0) -> 20871.91
A30: TXN-1517 | B30: 12/05/2024 | C30: Expense | D30: Cloud Infrastructure | E30: cloud infra | F30: Salary - AWS | G30: 37997.96 | H30: USD | I30: AWS | J30: Dec | K30: Q4 | N30: =IFERROR(VLOOKUP(TRIM(E30),$P$2:$Q$23,2,FALSE),"UNMAPPED - CHECK") -> Cloud Infrastructure | O30: =IFERROR(__xludf.DUMMYFUNCTION("IFERROR( IF(LEN(TRIM(B30))=6, DATE(2000+VALUE(RIGHT(TRIM(B30),2)),MATCH(LEFT(TRIM(B30),3),{""Jan"",""Feb"",""Mar"",""Apr"",""May"",""Jun"",""Jul"",""Aug"",""Sep"",""Oct"",""Nov"",""Dec""},0),15), IF(REGEXMATCH(TRIM(B30),""^\d{2}[/-]\d{2}[/-]\d{4}$"&"""), DATE(VALUE(RIGHT(TRIM(B30),4)),VALUE(MID(TRIM(B30),4,2)),VALUE(LEFT(TRIM(B30),2))), DATEVALUE(TRIM(B30)))), ""CHECK"")"),45424.0) -> 45424 | R30: =IF(O30="CHECK","CHECK",TEXT(O30,"mmm")) -> May | S30: =IF(O30="CHECK","CHECK","Q"&INT((MONTH(O30)-1)/3)+1) -> Q2 | T30: =IFERROR(IF(G30="see notes",IF(ISNUMBER(VALUE(L30)),VALUE(L30),0),IF(G30="",0,IF(H30="GBP",VALUE(G30)*1.27,IF(AND(ISNUMBER(VALUE(G30)),F30="Revenue",VALUE(G30)<0),ABS(VALUE(G30)),IF(ISNUMBER(VALUE(G30)),VALUE(G30),0))))),0) -> 37997.96
A31: TXN-1108 | B31: 2024-03-25 | C31: Expense | D31: Customer Success | E31: Customer Suc. | F31: AWS/Cloud - Randstad | G31: 22421.75 | H31: USD | I31: Randstad | J31: Mar | K31: Q1 | N31: =IFERROR(VLOOKUP(TRIM(E31),$P$2:$Q$23,2,FALSE),"UNMAPPED - CHECK") -> Customer Success | O31: =IFERROR(__xludf.DUMMYFUNCTION("IFERROR( IF(LEN(TRIM(B31))=6, DATE(2000+VALUE(RIGHT(TRIM(B31),2)),MATCH(LEFT(TRIM(B31),3),{""Jan"",""Feb"",""Mar"",""Apr"",""May"",""Jun"",""Jul"",""Aug"",""Sep"",""Oct"",""Nov"",""Dec""},0),15), IF(REGEXMATCH(TRIM(B31),""^\d{2}[/-]\d{2}[/-]\d{4}$"&"""), DATE(VALUE(RIGHT(TRIM(B31),4)),VALUE(MID(TRIM(B31),4,2)),VALUE(LEFT(TRIM(B31),2))), DATEVALUE(TRIM(B31)))), ""CHECK"")"),45376.0) -> 45376 | R31: =IF(O31="CHECK","CHECK",TEXT(O31,"mmm")) -> Mar | S31: =IF(O31="CHECK","CHECK","Q"&INT((MONTH(O31)-1)/3)+1) -> Q1 | T31: =IFERROR(IF(G31="see notes",IF(ISNUMBER(VALUE(L31)),VALUE(L31),0),IF(G31="",0,IF(H31="GBP",VALUE(G31)*1.27,IF(AND(ISNUMBER(VALUE(G31)),F31="Revenue",VALUE(G31)<0),ABS(VALUE(G31)),IF(ISNUMBER(VALUE(G31)),VALUE(G31),0))))),0) -> 22421.75
A32: TXN-1334 | B32: August 08, 2024 | C32: Expense | D32: Customer Success | E32: CS | F32: Travel - Slack | G32: 12571.55 | H32: USD | I32: Slack | J32: Aug | K32: Q3 | N32: =IFERROR(VLOOKUP(TRIM(E32),$P$2:$Q$23,2,FALSE),"UNMAPPED - CHECK") -> Customer Success | O32: =IFERROR(__xludf.DUMMYFUNCTION("IFERROR( IF(LEN(TRIM(B32))=6, DATE(2000+VALUE(RIGHT(TRIM(B32),2)),MATCH(LEFT(TRIM(B32),3),{""Jan"",""Feb"",""Mar"",""Apr"",""May"",""Jun"",""Jul"",""Aug"",""Sep"",""Oct"",""Nov"",""Dec""},0),15), IF(REGEXMATCH(TRIM(B32),""^\d{2}[/-]\d{2}[/-]\d{4}$"&"""), DATE(VALUE(RIGHT(TRIM(B32),4)),VALUE(MID(TRIM(B32),4,2)),VALUE(LEFT(TRIM(B32),2))), DATEVALUE(TRIM(B32)))), ""CHECK"")"),45512.0) -> 45512 | R32: =IF(O32="CHECK","CHECK",TEXT(O32,"mmm")) -> Aug | S32: =IF(O32="CHECK","CHECK","Q"&INT((MONTH(O32)-1)/3)+1) -> Q3 | T32: =IFERROR(IF(G32="see notes",IF(ISNUMBER(VALUE(L32)),VALUE(L32),0),IF(G32="",0,IF(H32="GBP",VALUE(G32)*1.27,IF(AND(ISNUMBER(VALUE(G32)),F32="Revenue",VALUE(G32)<0),ABS(VALUE(G32)),IF(ISNUMBER(VALUE(G32)),VALUE(G32),0))))),0) -> 12571.55
A33: TXN-1032 | B33: 22/01/2024 | C33: Expense | D33: G&A | E33: General & Admin | F33: Ad Spend - WeWork | G33: 12219.14 | H33: USD | I33: WeWork | J33: Jan | K33: Q1 | N33: =IFERROR(VLOOKUP(TRIM(E33),$P$2:$Q$23,2,FALSE),"UNMAPPED - CHECK") -> G&A | O33: =IFERROR(__xludf.DUMMYFUNCTION("IFERROR( IF(LEN(TRIM(B33))=6, DATE(2000+VALUE(RIGHT(TRIM(B33),2)),MATCH(LEFT(TRIM(B33),3),{""Jan"",""Feb"",""Mar"",""Apr"",""May"",""Jun"",""Jul"",""Aug"",""Sep"",""Oct"",""Nov"",""Dec""},0),15), IF(REGEXMATCH(TRIM(B33),""^\d{2}[/-]\d{2}[/-]\d{4}$"&"""), DATE(VALUE(RIGHT(TRIM(B33),4)),VALUE(MID(TRIM(B33),4,2)),VALUE(LEFT(TRIM(B33),2))), DATEVALUE(TRIM(B33)))), ""CHECK"")"),45313.0) -> 45313 | R33: =IF(O33="CHECK","CHECK",TEXT(O33,"mmm")) -> Jan | S33: =IF(O33="CHECK","CHECK","Q"&INT((MONTH(O33)-1)/3)+1) -> Q1 | T33: =IFERROR(IF(G33="see notes",IF(ISNUMBER(VALUE(L33)),VALUE(L33),0),IF(G33="",0,IF(H33="GBP",VALUE(G33)*1.27,IF(AND(ISNUMBER(VALUE(G33)),F33="Revenue",VALUE(G33)<0),ABS(VALUE(G33)),IF(ISNUMBER(VALUE(G33)),VALUE(G33),0))))),0) -> 12219.14
A34: TXN-1232 | B34: 06/06/2024 | C34: Expense | D34: Engineering | E34: Eng | F34: Software License - Linklaters LLP | G34: 30079.33 | H34: USD | I34: Linklaters LLP | J34: Jun | K34: Q2 | N34: =IFERROR(VLOOKUP(TRIM(E34),$P$2:$Q$23,2,FALSE),"UNMAPPED - CHECK") -> Engineering | O34: =IFERROR(__xludf.DUMMYFUNCTION("IFERROR( IF(LEN(TRIM(B34))=6, DATE(2000+VALUE(RIGHT(TRIM(B34),2)),MATCH(LEFT(TRIM(B34),3),{""Jan"",""Feb"",""Mar"",""Apr"",""May"",""Jun"",""Jul"",""Aug"",""Sep"",""Oct"",""Nov"",""Dec""},0),15), IF(REGEXMATCH(TRIM(B34),""^\d{2}[/-]\d{2}[/-]\d{4}$"&"""), DATE(VALUE(RIGHT(TRIM(B34),4)),VALUE(MID(TRIM(B34),4,2)),VALUE(LEFT(TRIM(B34),2))), DATEVALUE(TRIM(B34)))), ""CHECK"")"),45449.0) -> 45449 | R34: =IF(O34="CHECK","CHECK",TEXT(O34,"mmm")) -> Jun | S34: =IF(O34="CHECK","CHECK","Q"&INT((MONTH(O34)-1)/3)+1) -> Q2 | T34: =IFERROR(IF(G34="see notes",IF(ISNUMBER(VALUE(L34)),VALUE(L34),0),IF(G34="",0,IF(H34="GBP",VALUE(G34)*1.27,IF(AND(ISNUMBER(VALUE(G34)),F34="Revenue",VALUE(G34)<0),ABS(VALUE(G34)),IF(ISNUMBER(VALUE(G34)),VALUE(G34),0))))),0) -> 30079.33
A35: TXN-1159 | B35: 28-04-2024 | C35: Expense | D35: Cloud Infrastructure | E35: CLOUD | F35: Ad Spend - Delta Airlines | G35: 13746.82 | H35: USD | I35: Delta Airlines | J35: Apr | K35: Q2 | N35: =IFERROR(VLOOKUP(TRIM(E35),$P$2:$Q$23,2,FALSE),"UNMAPPED - CHECK") -> Cloud Infrastructure | O35: =IFERROR(__xludf.DUMMYFUNCTION("IFERROR( IF(LEN(TRIM(B35))=6, DATE(2000+VALUE(RIGHT(TRIM(B35),2)),MATCH(LEFT(TRIM(B35),3),{""Jan"",""Feb"",""Mar"",""Apr"",""May"",""Jun"",""Jul"",""Aug"",""Sep"",""Oct"",""Nov"",""Dec""},0),15), IF(REGEXMATCH(TRIM(B35),""^\d{2}[/-]\d{2}[/-]\d{4}$"&"""), DATE(VALUE(RIGHT(TRIM(B35),4)),VALUE(MID(TRIM(B35),4,2)),VALUE(LEFT(TRIM(B35),2))), DATEVALUE(TRIM(B35)))), ""CHECK"")"),45410.0) -> 45410 | R35: =IF(O35="CHECK","CHECK",TEXT(O35,"mmm")) -> Apr | S35: =IF(O35="CHECK","CHECK","Q"&INT((MONTH(O35)-1)/3)+1) -> Q2 | T35: =IFERROR(IF(G35="see notes",IF(ISNUMBER(VALUE(L35)),VALUE(L35),0),IF(G35="",0,IF(H35="GBP",VALUE(G35)*1.27,IF(AND(ISNUMBER(VALUE(G35)),F35="Revenue",VALUE(G35)<0),ABS(VALUE(G35)),IF(ISNUMBER(VALUE(G35)),VALUE(G35),0))))),0) -> 13746.82
A36: TXN-1118 | B36: 20-03-2024 | C36: Expense | D36: Cloud Infrastructure | E36: Cloud Infrastructure | F36: Travel - Slack | G36: 18874.72 | H36: USD | I36: Slack | J36: Mar | K36: Q1 | N36: =IFERROR(VLOOKUP(TRIM(E36),$P$2:$Q$23,2,FALSE),"UNMAPPED - CHECK") -> Cloud Infrastructure | O36: =IFERROR(__xludf.DUMMYFUNCTION("IFERROR( IF(LEN(TRIM(B36))=6, DATE(2000+VALUE(RIGHT(TRIM(B36),2)),MATCH(LEFT(TRIM(B36),3),{""Jan"",""Feb"",""Mar"",""Apr"",""May"",""Jun"",""Jul"",""Aug"",""Sep"",""Oct"",""Nov"",""Dec""},0),15), IF(REGEXMATCH(TRIM(B36),""^\d{2}[/-]\d{2}[/-]\d{4}$"&"""), DATE(VALUE(RIGHT(TRIM(B36),4)),VALUE(MID(TRIM(B36),4,2)),VALUE(LEFT(TRIM(B36),2))), DATEVALUE(TRIM(B36)))), ""CHECK"")"),45371.0) -> 45371 | R36: =IF(O36="CHECK","CHECK",TEXT(O36,"mmm")) -> Mar | S36: =IF(O36="CHECK","CHECK","Q"&INT((MONTH(O36)-1)/3)+1) -> Q1 | T36: =IFERROR(IF(G36="see notes",IF(ISNUMBER(VALUE(L36)),VALUE(L36),0),IF(G36="",0,IF(H36="GBP",VALUE(G36)*1.27,IF(AND(ISNUMBER(VALUE(G36)),F36="Revenue",VALUE(G36)<0),ABS(VALUE(G36)),IF(ISNUMBER(VALUE(G36)),VALUE(G36),0))))),0) -> 18874.72
A37: TXN-1211 | B37: 2024-06-28 | C37: Revenue | D37: Subscription | E37: SALES | F37: Subscription - Orion Media | G37: 144260.58 | H37: USD | I37: Priya Nair | J37: Jun | K37: Q2 | N37: =IFERROR(VLOOKUP(TRIM(E37),$P$2:$Q$23,2,FALSE),"UNMAPPED - CHECK") -> Sales | O37: =IFERROR(__xludf.DUMMYFUNCTION("IFERROR( IF(LEN(TRIM(B37))=6, DATE(2000+VALUE(RIGHT(TRIM(B37),2)),MATCH(LEFT(TRIM(B37),3),{""Jan"",""Feb"",""Mar"",""Apr"",""May"",""Jun"",""Jul"",""Aug"",""Sep"",""Oct"",""Nov"",""Dec""},0),15), IF(REGEXMATCH(TRIM(B37),""^\d{2}[/-]\d{2}[/-]\d{4}$"&"""), DATE(VALUE(RIGHT(TRIM(B37),4)),VALUE(MID(TRIM(B37),4,2)),VALUE(LEFT(TRIM(B37),2))), DATEVALUE(TRIM(B37)))), ""CHECK"")"),45471.0) -> 45471 | R37: =IF(O37="CHECK","CHECK",TEXT(O37,"mmm")) -> Jun | S37: =IF(O37="CHECK","CHECK","Q"&INT((MONTH(O37)-1)/3)+1) -> Q2 | T37: =IFERROR(IF(G37="see notes",IF(ISNUMBER(VALUE(L37)),VALUE(L37),0),IF(G37="",0,IF(H37="GBP",VALUE(G37)*1.27,IF(AND(ISNUMBER(VALUE(G37)),F37="Revenue",VALUE(G37)<0),ABS(VALUE(G37)),IF(ISNUMBER(VALUE(G37)),VALUE(G37),0))))),0) -> 144260.58
A38: TXN-1352 | B38: September 19, 2024 | C38: Revenue | D38: Professional Services | E38: SALES | F38: Professional Services - Vertex Analytics | G38: 24777.81 | H38: USD | I38: James Okafor | J38: Sep | K38: Q3 | N38: =IFERROR(VLOOKUP(TRIM(E38),$P$2:$Q$23,2,FALSE),"UNMAPPED - CHECK") -> Sales | O38: =IFERROR(__xludf.DUMMYFUNCTION("IFERROR( IF(LEN(TRIM(B38))=6, DATE(2000+VALUE(RIGHT(TRIM(B38),2)),MATCH(LEFT(TRIM(B38),3),{""Jan"",""Feb"",""Mar"",""Apr"",""May"",""Jun"",""Jul"",""Aug"",""Sep"",""Oct"",""Nov"",""Dec""},0),15), IF(REGEXMATCH(TRIM(B38),""^\d{2}[/-]\d{2}[/-]\d{4}$"&"""), DATE(VALUE(RIGHT(TRIM(B38),4)),VALUE(MID(TRIM(B38),4,2)),VALUE(LEFT(TRIM(B38),2))), DATEVALUE(TRIM(B38)))), ""CHECK"")"),45554.0) -> 45554 | R38: =IF(O38="CHECK","CHECK",TEXT(O38,"mmm")) -> Sep | S38: =IF(O38="CHECK","CHECK","Q"&INT((MONTH(O38)-1)/3)+1) -> Q3 | T38: =IFERROR(IF(G38="see notes",IF(ISNUMBER(VALUE(L38)),VALUE(L38),0),IF(G38="",0,IF(H38="GBP",VALUE(G38)*1.27,IF(AND(ISNUMBER(VALUE(G38)),F38="Revenue",VALUE(G38)<0),ABS(VALUE(G38)),IF(ISNUMBER(VALUE(G38)),VALUE(G38),0))))),0) -> 24777.81
A39: TXN-1374 | B39: 19-09-2024 | C39: Expense | D39: Customer Success | E39: CS | F39: Travel - Linklaters LLP | G39: 27990.06 | H39: USD | I39: Linklaters LLP | J39: Sep | K39: Q3 | N39: =IFERROR(VLOOKUP(TRIM(E39),$P$2:$Q$23,2,FALSE),"UNMAPPED - CHECK") -> Customer Success | O39: =IFERROR(__xludf.DUMMYFUNCTION("IFERROR( IF(LEN(TRIM(B39))=6, DATE(2000+VALUE(RIGHT(TRIM(B39),2)),MATCH(LEFT(TRIM(B39),3),{""Jan"",""Feb"",""Mar"",""Apr"",""May"",""Jun"",""Jul"",""Aug"",""Sep"",""Oct"",""Nov"",""Dec""},0),15), IF(REGEXMATCH(TRIM(B39),""^\d{2}[/-]\d{2}[/-]\d{4}$"&"""), DATE(VALUE(RIGHT(TRIM(B39),4)),VALUE(MID(TRIM(B39),4,2)),VALUE(LEFT(TRIM(B39),2))), DATEVALUE(TRIM(B39)))), ""CHECK"")"),45554.0) -> 45554 | R39: =IF(O39="CHECK","CHECK",TEXT(O39,"mmm")) -> Sep | S39: =IF(O39="CHECK","CHECK","Q"&INT((MONTH(O39)-1)/3)+1) -> Q3 | T39: =IFERROR(IF(G39="see notes",IF(ISNUMBER(VALUE(L39)),VALUE(L39),0),IF(G39="",0,IF(H39="GBP",VALUE(G39)*1.27,IF(AND(ISNUMBER(VALUE(G39)),F39="Revenue",VALUE(G39)<0),ABS(VALUE(G39)),IF(ISNUMBER(VALUE(G39)),VALUE(G39),0))))),0) -> 27990.06
A40: TXN-1229 | B40: 06/03/2024 | C40: Expense | D40: Marketing | E40: MARKETING | F40: AWS/Cloud - WeWork | G40: 58324.51 | H40: USD | I40: WeWork | J40: Jun | K40: Q2 | N40: =IFERROR(VLOOKUP(TRIM(E40),$P$2:$Q$23,2,FALSE),"UNMAPPED - CHECK") -> Marketing | O40: =IFERROR(__xludf.DUMMYFUNCTION("IFERROR( IF(LEN(TRIM(B40))=6, DATE(2000+VALUE(RIGHT(TRIM(B40),2)),MATCH(LEFT(TRIM(B40),3),{""Jan"",""Feb"",""Mar"",""Apr"",""May"",""Jun"",""Jul"",""Aug"",""Sep"",""Oct"",""Nov"",""Dec""},0),15), IF(REGEXMATCH(TRIM(B40),""^\d{2}[/-]\d{2}[/-]\d{4}$"&"""), DATE(VALUE(RIGHT(TRIM(B40),4)),VALUE(MID(TRIM(B40),4,2)),VALUE(LEFT(TRIM(B40),2))), DATEVALUE(TRIM(B40)))), ""CHECK"")"),45357.0) -> 45357 | R40: =IF(O40="CHECK","CHECK",TEXT(O40,"mmm")) -> Mar | S40: =IF(O40="CHECK","CHECK","Q"&INT((MONTH(O40)-1)/3)+1) -> Q1 | T40: =IFERROR(IF(G40="see notes",IF(ISNUMBER(VALUE(L40)),VALUE(L40),0),IF(G40="",0,IF(H40="GBP",VALUE(G40)*1.27,IF(AND(ISNUMBER(VALUE(G40)),F40="Revenue",VALUE(G40)<0),ABS(VALUE(G40)),IF(ISNUMBER(VALUE(G40)),VALUE(G40),0))))),0) -> 58324.51
A41: TXN-1212 | B41: 01-06-2024 | C41: Revenue | D41: Professional Services | E41: SALES | F41: Professional Services - Vertex Analytics | G41: 28569.62 | H41: USD | I41: Daniel Müller | J41: Jun | K41: Q2 | N41: =IFERROR(VLOOKUP(TRIM(E41),$P$2:$Q$23,2,FALSE),"UNMAPPED - CHECK") -> Sales | O41: =IFERROR(__xludf.DUMMYFUNCTION("IFERROR( IF(LEN(TRIM(B41))=6, DATE(2000+VALUE(RIGHT(TRIM(B41),2)),MATCH(LEFT(TRIM(B41),3),{""Jan"",""Feb"",""Mar"",""Apr"",""May"",""Jun"",""Jul"",""Aug"",""Sep"",""Oct"",""Nov"",""Dec""},0),15), IF(REGEXMATCH(TRIM(B41),""^\d{2}[/-]\d{2}[/-]\d{4}$"&"""), DATE(VALUE(RIGHT(TRIM(B41),4)),VALUE(MID(TRIM(B41),4,2)),VALUE(LEFT(TRIM(B41),2))), DATEVALUE(TRIM(B41)))), ""CHECK"")"),45444.0) -> 45444 | R41: =IF(O41="CHECK","CHECK",TEXT(O41,"mmm")) -> Jun | S41: =IF(O41="CHECK","CHECK","Q"&INT((MONTH(O41)-1)/3)+1) -> Q2 | T41: =IFERROR(IF(G41="see notes",IF(ISNUMBER(VALUE(L41)),VALUE(L41),0),IF(G41="",0,IF(H41="GBP",VALUE(G41)*1.27,IF(AND(ISNUMBER(VALUE(G41)),F41="Revenue",VALUE(G41)<0),ABS(VALUE(G41)),IF(ISNUMBER(VALUE(G41)),VALUE(G41),0))))),0) -> 28569.62
A42: TXN-1280 | B42: 15/07/2024 | C42: Expense | D42: Engineering | E42: engineering | F42: Office Supplies - WeWork | G42: 17996.1 | H42: USD | I42: WeWork | J42: Jul | K42: Q3 | N42: =IFERROR(VLOOKUP(TRIM(E42),$P$2:$Q$23,2,FALSE),"UNMAPPED - CHECK") -> Engineering | O42: =IFERROR(__xludf.DUMMYFUNCTION("IFERROR( IF(LEN(TRIM(B42))=6, DATE(2000+VALUE(RIGHT(TRIM(B42),2)),MATCH(LEFT(TRIM(B42),3),{""Jan"",""Feb"",""Mar"",""Apr"",""May"",""Jun"",""Jul"",""Aug"",""Sep"",""Oct"",""Nov"",""Dec""},0),15), IF(REGEXMATCH(TRIM(B42),""^\d{2}[/-]\d{2}[/-]\d{4}$"&"""), DATE(VALUE(RIGHT(TRIM(B42),4)),VALUE(MID(TRIM(B42),4,2)),VALUE(LEFT(TRIM(B42),2))), DATEVALUE(TRIM(B42)))), ""CHECK"")"),45488.0) -> 45488 | R42: =IF(O42="CHECK","CHECK",TEXT(O42,"mmm")) -> Jul | S42: =IF(O42="CHECK","CHECK","Q"&INT((MONTH(O42)-1)/3)+1) -> Q3 | T42: =IFERROR(IF(G42="see notes",IF(ISNUMBER(VALUE(L42)),VALUE(L42),0),IF(G42="",0,IF(H42="GBP",VALUE(G42)*1.27,IF(AND(ISNUMBER(VALUE(G42)),F42="Revenue",VALUE(G42)<0),ABS(VALUE(G42)),IF(ISNUMBER(VALUE(G42)),VALUE(G42),0))))),0) -> 17996.1
A43: TXN-1148 | B43: 04/16/2024 | C43: Expense | D43: Engineering | E43: R&D | F43: Legal - HubSpot | G43: 36377.1 | H43: USD | I43: HubSpot | J43: Apr | K43: Q2 | N43: =IFERROR(VLOOKUP(TRIM(E43),$P$2:$Q$23,2,FALSE),"UNMAPPED - CHECK") -> Engineering | O43: =IFERROR(__xludf.DUMMYFUNCTION("IFERROR( IF(LEN(TRIM(B43))=6, DATE(2000+VALUE(RIGHT(TRIM(B43),2)),MATCH(LEFT(TRIM(B43),3),{""Jan"",""Feb"",""Mar"",""Apr"",""May"",""Jun"",""Jul"",""Aug"",""Sep"",""Oct"",""Nov"",""Dec""},0),15), IF(REGEXMATCH(TRIM(B43),""^\d{2}[/-]\d{2}[/-]\d{4}$"&"""), DATE(VALUE(RIGHT(TRIM(B43),4)),VALUE(MID(TRIM(B43),4,2)),VALUE(LEFT(TRIM(B43),2))), DATEVALUE(TRIM(B43)))), ""CHECK"")"),45751.0) -> 45751 | R43: =IF(O43="CHECK","CHECK",TEXT(O43,"mmm")) -> Apr | S43: =IF(O43="CHECK","CHECK","Q"&INT((MONTH(O43)-1)/3)+1) -> Q2 | T43: =IFERROR(IF(G43="see notes",IF(ISNUMBER(VALUE(L43)),VALUE(L43),0),IF(G43="",0,IF(H43="GBP",VALUE(G43)*1.27,IF(AND(ISNUMBER(VALUE(G43)),F43="Revenue",VALUE(G43)<0),ABS(VALUE(G43)),IF(ISNUMBER(VALUE(G43)),VALUE(G43),0))))),0) -> 36377.1
A44: TXN-1145 | B44: 2024-04-18 | C44: Expense | D44: Engineering | E44: Engineering | F44: Travel - WeWork | G44: 26734.12 | H44: USD | I44: WeWork | N44: =IFERROR(VLOOKUP(TRIM(E44),$P$2:$Q$23,2,FALSE),"UNMAPPED - CHECK") -> Engineering | O44: =IFERROR(__xludf.DUMMYFUNCTION("IFERROR( IF(LEN(TRIM(B44))=6, DATE(2000+VALUE(RIGHT(TRIM(B44),2)),MATCH(LEFT(TRIM(B44),3),{""Jan"",""Feb"",""Mar"",""Apr"",""May"",""Jun"",""Jul"",""Aug"",""Sep"",""Oct"",""Nov"",""Dec""},0),15), IF(REGEXMATCH(TRIM(B44),""^\d{2}[/-]\d{2}[/-]\d{4}$"&"""), DATE(VALUE(RIGHT(TRIM(B44),4)),VALUE(MID(TRIM(B44),4,2)),VALUE(LEFT(TRIM(B44),2))), DATEVALUE(TRIM(B44)))), ""CHECK"")"),45400.0) -> 45400 | R44: =IF(O44="CHECK","CHECK",TEXT(O44,"mmm")) -> Apr | S44: =IF(O44="CHECK","CHECK","Q"&INT((MONTH(O44)-1)/3)+1) -> Q2 | T44: =IFERROR(IF(G44="see notes",IF(ISNUMBER(VALUE(L44)),VALUE(L44),0),IF(G44="",0,IF(H44="GBP",VALUE(G44)*1.27,IF(AND(ISNUMBER(VALUE(G44)),F44="Revenue",VALUE(G44)<0),ABS(VALUE(G44)),IF(ISNUMBER(VALUE(G44)),VALUE(G44),0))))),0) -> 26734.12
A45: TXN-1094 | B45: 15-03-2024 | C45: Revenue | D45: Licensing | E45: Sales Dept | F45: Licensing - Orion Media | G45: 6371.57 | H45: USD | I45: Lena Fischer | J45: Mar | K45: Q1 | N45: =IFERROR(VLOOKUP(TRIM(E45),$P$2:$Q$23,2,FALSE),"UNMAPPED - CHECK") -> Sales | O45: =IFERROR(__xludf.DUMMYFUNCTION("IFERROR( IF(LEN(TRIM(B45))=6, DATE(2000+VALUE(RIGHT(TRIM(B45),2)),MATCH(LEFT(TRIM(B45),3),{""Jan"",""Feb"",""Mar"",""Apr"",""May"",""Jun"",""Jul"",""Aug"",""Sep"",""Oct"",""Nov"",""Dec""},0),15), IF(REGEXMATCH(TRIM(B45),""^\d{2}[/-]\d{2}[/-]\d{4}$"&"""), DATE(VALUE(RIGHT(TRIM(B45),4)),VALUE(MID(TRIM(B45),4,2)),VALUE(LEFT(TRIM(B45),2))), DATEVALUE(TRIM(B45)))), ""CHECK"")"),45366.0) -> 45366 | R45: =IF(O45="CHECK","CHECK",TEXT(O45,"mmm")) -> Mar | S45: =IF(O45="CHECK","CHECK","Q"&INT((MONTH(O45)-1)/3)+1) -> Q1 | T45: =IFERROR(IF(G45="see notes",IF(ISNUMBER(VALUE(L45)),VALUE(L45),0),IF(G45="",0,IF(H45="GBP",VALUE(G45)*1.27,IF(AND(ISNUMBER(VALUE(G45)),F45="Revenue",VALUE(G45)<0),ABS(VALUE(G45)),IF(ISNUMBER(VALUE(G45)),VALUE(G45),0))))),0) -> 6371.57
A46: TXN-1168 | B46: 28/05/2024 | C46: Revenue | D46: Professional Services | E46: Sales Dept | F46: Professional Services - TechNova Ltd | G46: 14601.16 | H46: USD | I46: Kwame Asante | J46: May | K46: Q2 | N46: =IFERROR(VLOOKUP(TRIM(E46),$P$2:$Q$23,2,FALSE),"UNMAPPED - CHECK") -> Sales | O46: =IFERROR(__xludf.DUMMYFUNCTION("IFERROR( IF(LEN(TRIM(B46))=6, DATE(2000+VALUE(RIGHT(TRIM(B46),2)),MATCH(LEFT(TRIM(B46),3),{""Jan"",""Feb"",""Mar"",""Apr"",""May"",""Jun"",""Jul"",""Aug"",""Sep"",""Oct"",""Nov"",""Dec""},0),15), IF(REGEXMATCH(TRIM(B46),""^\d{2}[/-]\d{2}[/-]\d{4}$"&"""), DATE(VALUE(RIGHT(TRIM(B46),4)),VALUE(MID(TRIM(B46),4,2)),VALUE(LEFT(TRIM(B46),2))), DATEVALUE(TRIM(B46)))), ""CHECK"")"),45440.0) -> 45440 | R46: =IF(O46="CHECK","CHECK",TEXT(O46,"mmm")) -> May | S46: =IF(O46="CHECK","CHECK","Q"&INT((MONTH(O46)-1)/3)+1) -> Q2 | T46: =IFERROR(IF(G46="see notes",IF(ISNUMBER(VALUE(L46)),VALUE(L46),0),IF(G46="",0,IF(H46="GBP",VALUE(G46)*1.27,IF(AND(ISNUMBER(VALUE(G46)),F46="Revenue",VALUE(G46)<0),ABS(VALUE(G46)),IF(ISNUMBER(VALUE(G46)),VALUE(G46),0))))),0) -> 14601.16
A47: TXN-1220 | B47: 22/06/2024 | C47: Revenue | D47: Licensing | E47: sales | F47: Licensing - Altura Health | G47: 8918.29 | H47: USD | I47: Kwame Asante | J47: Jun | K47: Q2 | N47: =IFERROR(VLOOKUP(TRIM(E47),$P$2:$Q$23,2,FALSE),"UNMAPPED - CHECK") -> Sales | O47: =IFERROR(__xludf.DUMMYFUNCTION("IFERROR( IF(LEN(TRIM(B47))=6, DATE(2000+VALUE(RIGHT(TRIM(B47),2)),MATCH(LEFT(TRIM(B47),3),{""Jan"",""Feb"",""Mar"",""Apr"",""May"",""Jun"",""Jul"",""Aug"",""Sep"",""Oct"",""Nov"",""Dec""},0),15), IF(REGEXMATCH(TRIM(B47),""^\d{2}[/-]\d{2}[/-]\d{4}$"&"""), DATE(VALUE(RIGHT(TRIM(B47),4)),VALUE(MID(TRIM(B47),4,2)),VALUE(LEFT(TRIM(B47),2))), DATEVALUE(TRIM(B47)))), ""CHECK"")"),45465.0) -> 45465 | R47: =IF(O47="CHECK","CHECK",TEXT(O47,"mmm")) -> Jun | S47: =IF(O47="CHECK","CHECK","Q"&INT((MONTH(O47)-1)/3)+1) -> Q2 | T47: =IFERROR(IF(G47="see notes",IF(ISNUMBER(VALUE(L47)),VALUE(L47),0),IF(G47="",0,IF(H47="GBP",VALUE(G47)*1.27,IF(AND(ISNUMBER(VALUE(G47)),F47="Revenue",VALUE(G47)<0),ABS(VALUE(G47)),IF(ISNUMBER(VALUE(G47)),VALUE(G47),0))))),0) -> 8918.29
A48: TXN-1222 | B48: 07-06-2024 | C48: Revenue | D48: Licensing | E48: SALES | F48: Licensing - Vertex Analytics | G48: 6040.53 | H48: USD | I48: Daniel Müller | J48: Jun | K48: Q2 | N48: =IFERROR(VLOOKUP(TRIM(E48),$P$2:$Q$23,2,FALSE),"UNMAPPED - CHECK") -> Sales | O48: =IFERROR(__xludf.DUMMYFUNCTION("IFERROR( IF(LEN(TRIM(B48))=6, DATE(2000+VALUE(RIGHT(TRIM(B48),2)),MATCH(LEFT(TRIM(B48),3),{""Jan"",""Feb"",""Mar"",""Apr"",""May"",""Jun"",""Jul"",""Aug"",""Sep"",""Oct"",""Nov"",""Dec""},0),15), IF(REGEXMATCH(TRIM(B48),""^\d{2}[/-]\d{2}[/-]\d{4}$"&"""), DATE(VALUE(RIGHT(TRIM(B48),4)),VALUE(MID(TRIM(B48),4,2)),VALUE(LEFT(TRIM(B48),2))), DATEVALUE(TRIM(B48)))), ""CHECK"")"),45450.0) -> 45450 | R48: =IF(O48="CHECK","CHECK",TEXT(O48,"mmm")) -> Jun | S48: =IF(O48="CHECK","CHECK","Q"&INT((MONTH(O48)-1)/3)+1) -> Q2 | T48: =IFERROR(IF(G48="see notes",IF(ISNUMBER(VALUE(L48)),VALUE(L48),0),IF(G48="",0,IF(H48="GBP",VALUE(G48)*1.27,IF(AND(ISNUMBER(VALUE(G48)),F48="Revenue",VALUE(G48)<0),ABS(VALUE(G48)),IF(ISNUMBER(VALUE(G48)),VALUE(G48),0))))),0) -> 6040.53
A49: TXN-1091 | B49: 2024-03-20 | C49: Revenue | D49: Licensing | E49: Sales | F49: Licensing - ClearPath Finance | G49: 7976.65 | H49: USD | I49: James Okafor | J49: Mar | K49: Q1 | N49: =IFERROR(VLOOKUP(TRIM(E49),$P$2:$Q$23,2,FALSE),"UNMAPPED - CHECK") -> Sales | O49: =IFERROR(__xludf.DUMMYFUNCTION("IFERROR( IF(LEN(TRIM(B49))=6, DATE(2000+VALUE(RIGHT(TRIM(B49),2)),MATCH(LEFT(TRIM(B49),3),{""Jan"",""Feb"",""Mar"",""Apr"",""May"",""Jun"",""Jul"",""Aug"",""Sep"",""Oct"",""Nov"",""Dec""},0),15), IF(REGEXMATCH(TRIM(B49),""^\d{2}[/-]\d{2}[/-]\d{4}$"&"""), DATE(VALUE(RIGHT(TRIM(B49),4)),VALUE(MID(TRIM(B49),4,2)),VALUE(LEFT(TRIM(B49),2))), DATEVALUE(TRIM(B49)))), ""CHECK"")"),45371.0) -> 45371 | R49: =IF(O49="CHECK","CHECK",TEXT(O49,"mmm")) -> Mar | S49: =IF(O49="CHECK","CHECK","Q"&INT((MONTH(O49)-1)/3)+1) -> Q1 | T49: =IFERROR(IF(G49="see notes",IF(ISNUMBER(VALUE(L49)),VALUE(L49),0),IF(G49="",0,IF(H49="GBP",VALUE(G49)*1.27,IF(AND(ISNUMBER(VALUE(G49)),F49="Revenue",VALUE(G49)<0),ABS(VALUE(G49)),IF(ISNUMBER(VALUE(G49)),VALUE(G49),0))))),0) -> 7976.65
A50: TXN-1478 | B50: December 10, 2024 | C50: Revenue | D50: Subscription | E50: Sales | F50: Subscription - Vertex Analytics | G50: 192445.88 | H50: USD | I50: Daniel Müller | J50: Dec | K50: Q4 | N50: =IFERROR(VLOOKUP(TRIM(E50),$P$2:$Q$23,2,FALSE),"UNMAPPED - CHECK") -> Sales | O50: =IFERROR(__xludf.DUMMYFUNCTION("IFERROR( IF(LEN(TRIM(B50))=6, DATE(2000+VALUE(RIGHT(TRIM(B50),2)),MATCH(LEFT(TRIM(B50),3),{""Jan"",""Feb"",""Mar"",""Apr"",""May"",""Jun"",""Jul"",""Aug"",""Sep"",""Oct"",""Nov"",""Dec""},0),15), IF(REGEXMATCH(TRIM(B50),""^\d{2}[/-]\d{2}[/-]\d{4}$"&"""), DATE(VALUE(RIGHT(TRIM(B50),4)),VALUE(MID(TRIM(B50),4,2)),VALUE(LEFT(TRIM(B50),2))), DATEVALUE(TRIM(B50)))), ""CHECK"")"),45636.0) -> 45636 | R50: =IF(O50="CHECK","CHECK",TEXT(O50,"mmm")) -> Dec | S50: =IF(O50="CHECK","CHECK","Q"&INT((MONTH(O50)-1)/3)+1) -> Q4 | T50: =IFERROR(IF(G50="see notes",IF(ISNUMBER(VALUE(L50)),VALUE(L50),0),IF(G50="",0,IF(H50="GBP",VALUE(G50)*1.27,IF(AND(ISNUMBER(VALUE(G50)),F50="Revenue",VALUE(G50)<0),ABS(VALUE(G50)),IF(ISNUMBER(VALUE(G50)),VALUE(G50),0))))),0) -> 192445.88
A51: TXN-1035 | B51: 2024-01-28 | C51: Expense | D51: Cloud Infrastructure | E51: cloud infra | F51: Legal - Google Cloud | G51: 46810.09 | H51: USD | I51: Google Cloud | J51: Jan | K51: Q1 | N51: =IFERROR(VLOOKUP(TRIM(E51),$P$2:$Q$23,2,FALSE),"UNMAPPED - CHECK") -> Cloud Infrastructure | O51: =IFERROR(__xludf.DUMMYFUNCTION("IFERROR( IF(LEN(TRIM(B51))=6, DATE(2000+VALUE(RIGHT(TRIM(B51),2)),MATCH(LEFT(TRIM(B51),3),{""Jan"",""Feb"",""Mar"",""Apr"",""May"",""Jun"",""Jul"",""Aug"",""Sep"",""Oct"",""Nov"",""Dec""},0),15), IF(REGEXMATCH(TRIM(B51),""^\d{2}[/-]\d{2}[/-]\d{4}$"&"""), DATE(VALUE(RIGHT(TRIM(B51),4)),VALUE(MID(TRIM(B51),4,2)),VALUE(LEFT(TRIM(B51),2))), DATEVALUE(TRIM(B51)))), ""CHECK"")"),45319.0) -> 45319 | R51: =IF(O51="CHECK","CHECK",TEXT(O51,"mmm")) -> Jan | S51: =IF(O51="CHECK","CHECK","Q"&INT((MONTH(O51)-1)/3)+1) -> Q1 | T51: =IFERROR(IF(G51="see notes",IF(ISNUMBER(VALUE(L51)),VALUE(L51),0),IF(G51="",0,IF(H51="GBP",VALUE(G51)*1.27,IF(AND(ISNUMBER(VALUE(G51)),F51="Revenue",VALUE(G51)<0),ABS(VALUE(G51)),IF(ISNUMBER(VALUE(G51)),VALUE(G51),0))))),0) -> 46810.09
A52: TXN-1246 | B52: 19-06-2024 | C52: Expense | D52: Cloud Infrastructure | E52: Cloud Infra | F52: AWS/Cloud - Delta Airlines | G52: 26973.1 | H52: USD | I52: Delta Airlines | J52: Jun | K52: Q2 | N52: =IFERROR(VLOOKUP(TRIM(E52),$P$2:$Q$23,2,FALSE),"UNMAPPED - CHECK") -> Cloud Infrastructure | O52: =IFERROR(__xludf.DUMMYFUNCTION("IFERROR( IF(LEN(TRIM(B52))=6, DATE(2000+VALUE(RIGHT(TRIM(B52),2)),MATCH(LEFT(TRIM(B52),3),{""Jan"",""Feb"",""Mar"",""Apr"",""May"",""Jun"",""Jul"",""Aug"",""Sep"",""Oct"",""Nov"",""Dec""},0),15), IF(REGEXMATCH(TRIM(B52),""^\d{2}[/-]\d{2}[/-]\d{4}$"&"""), DATE(VALUE(RIGHT(TRIM(B52),4)),VALUE(MID(TRIM(B52),4,2)),VALUE(LEFT(TRIM(B52),2))), DATEVALUE(TRIM(B52)))), ""CHECK"")"),45462.0) -> 45462 | R52: =IF(O52="CHECK","CHECK",TEXT(O52,"mmm")) -> Jun | S52: =IF(O52="CHECK","CHECK","Q"&INT((MONTH(O52)-1)/3)+1) -> Q2 | T52: =IFERROR(IF(G52="see notes",IF(ISNUMBER(VALUE(L52)),VALUE(L52),0),IF(G52="",0,IF(H52="GBP",VALUE(G52)*1.27,IF(AND(ISNUMBER(VALUE(G52)),F52="Revenue",VALUE(G52)<0),ABS(VALUE(G52)),IF(ISNUMBER(VALUE(G52)),VALUE(G52),0))))),0) -> 26973.1
A53: TXN-1318 | B53: August 25, 2024 | C53: Expense | D53: Sales | E53: SALES | F53: Recruiting - Omnicom Group | G53: 10669.47 | H53: USD | I53: Omnicom Group | J53: Aug | K53: Q3 | N53: =IFERROR(VLOOKUP(TRIM(E53),$P$2:$Q$23,2,FALSE),"UNMAPPED - CHECK") -> Sales | O53: =IFERROR(__xludf.DUMMYFUNCTION("IFERROR( IF(LEN(TRIM(B53))=6, DATE(2000+VALUE(RIGHT(TRIM(B53),2)),MATCH(LEFT(TRIM(B53),3),{""Jan"",""Feb"",""Mar"",""Apr"",""May"",""Jun"",""Jul"",""Aug"",""Sep"",""Oct"",""Nov"",""Dec""},0),15), IF(REGEXMATCH(TRIM(B53),""^\d{2}[/-]\d{2}[/-]\d{4}$"&"""), DATE(VALUE(RIGHT(TRIM(B53),4)),VALUE(MID(TRIM(B53),4,2)),VALUE(LEFT(TRIM(B53),2))), DATEVALUE(TRIM(B53)))), ""CHECK"")"),45529.0) -> 45529 | R53: =IF(O53="CHECK","CHECK",TEXT(O53,"mmm")) -> Aug | S53: =IF(O53="CHECK","CHECK","Q"&INT((MONTH(O53)-1)/3)+1) -> Q3 | T53: =IFERROR(IF(G53="see notes",IF(ISNUMBER(VALUE(L53)),VALUE(L53),0),IF(G53="",0,IF(H53="GBP",VALUE(G53)*1.27,IF(AND(ISNUMBER(VALUE(G53)),F53="Revenue",VALUE(G53)<0),ABS(VALUE(G53)),IF(ISNUMBER(VALUE(G53)),VALUE(G53),0))))),0) -> 10669.47
A54: TXN-1486 | B54: Dec-24 | C54: Revenue | D54: Professional Services | E54: Sales | F54: Professional Services - Globex Corp | G54: 24516.69 | H54: USD | I54: Daniel Müller | J54: Dec | K54: Q4 | N54: =IFERROR(VLOOKUP(TRIM(E54),$P$2:$Q$23,2,FALSE),"UNMAPPED - CHECK") -> Sales | O54: =IFERROR(__xludf.DUMMYFUNCTION("IFERROR( IF(LEN(TRIM(B54))=6, DATE(2000+VALUE(RIGHT(TRIM(B54),2)),MATCH(LEFT(TRIM(B54),3),{""Jan"",""Feb"",""Mar"",""Apr"",""May"",""Jun"",""Jul"",""Aug"",""Sep"",""Oct"",""Nov"",""Dec""},0),15), IF(REGEXMATCH(TRIM(B54),""^\d{2}[/-]\d{2}[/-]\d{4}$"&"""), DATE(VALUE(RIGHT(TRIM(B54),4)),VALUE(MID(TRIM(B54),4,2)),VALUE(LEFT(TRIM(B54),2))), DATEVALUE(TRIM(B54)))), ""CHECK"")"),45641.0) -> 45641 | R54: =IF(O54="CHECK","CHECK",TEXT(O54,"mmm")) -> Dec | S54: =IF(O54="CHECK","CHECK","Q"&INT((MONTH(O54)-1)/3)+1) -> Q4 | T54: =IFERROR(IF(G54="see notes",IF(ISNUMBER(VALUE(L54)),VALUE(L54),0),IF(G54="",0,IF(H54="GBP",VALUE(G54)*1.27,IF(AND(ISNUMBER(VALUE(G54)),F54="Revenue",VALUE(G54)<0),ABS(VALUE(G54)),IF(ISNUMBER(VALUE(G54)),VALUE(G54),0))))),0) -> 24516.69
A55: TXN-1448 | B55: 20-11-2024 | C55: Revenue | D55: Licensing | E55: Sales | F55: Licensing - BlueSky Logistics | G55: 6484.32 | H55: USD | I55: Aisha Rahman | J55: Nov | K55: Q4 | N55: =IFERROR(VLOOKUP(TRIM(E55),$P$2:$Q$23,2,FALSE),"UNMAPPED - CHECK") -> Sales | O55: =IFERROR(__xludf.DUMMYFUNCTION("IFERROR( IF(LEN(TRIM(B55))=6, DATE(2000+VALUE(RIGHT(TRIM(B55),2)),MATCH(LEFT(TRIM(B55),3),{""Jan"",""Feb"",""Mar"",""Apr"",""May"",""Jun"",""Jul"",""Aug"",""Sep"",""Oct"",""Nov"",""Dec""},0),15), IF(REGEXMATCH(TRIM(B55),""^\d{2}[/-]\d{2}[/-]\d{4}$"&"""), DATE(VALUE(RIGHT(TRIM(B55),4)),VALUE(MID(TRIM(B55),4,2)),VALUE(LEFT(TRIM(B55),2))), DATEVALUE(TRIM(B55)))), ""CHECK"")"),45616.0) -> 45616 | R55: =IF(O55="CHECK","CHECK",TEXT(O55,"mmm")) -> Nov | S55: =IF(O55="CHECK","CHECK","Q"&INT((MONTH(O55)-1)/3)+1) -> Q4 | T55: =IFERROR(IF(G55="see notes",IF(ISNUMBER(VALUE(L55)),VALUE(L55),0),IF(G55="",0,IF(H55="GBP",VALUE(G55)*1.27,IF(AND(ISNUMBER(VALUE(G55)),F55="Revenue",VALUE(G55)<0),ABS(VALUE(G55)),IF(ISNUMBER(VALUE(G55)),VALUE(G55),0))))),0) -> 6484.32
A56: TXN-1301 | B56: 08/31/2024 | C56: Revenue | D56: Subscription | E56: SALES | F56: Subscription - Globex Corp | G56: 234800.48 | H56: USD | I56: Kwame Asante | J56: Aug | K56: Q3 | N56: =IFERROR(VLOOKUP(TRIM(E56),$P$2:$Q$23,2,FALSE),"UNMAPPED - CHECK") -> Sales | O56: =IFERROR(__xludf.DUMMYFUNCTION("IFERROR( IF(LEN(TRIM(B56))=6, DATE(2000+VALUE(RIGHT(TRIM(B56),2)),MATCH(LEFT(TRIM(B56),3),{""Jan"",""Feb"",""Mar"",""Apr"",""May"",""Jun"",""Jul"",""Aug"",""Sep"",""Oct"",""Nov"",""Dec""},0),15), IF(REGEXMATCH(TRIM(B56),""^\d{2}[/-]\d{2}[/-]\d{4}$"&"""), DATE(VALUE(RIGHT(TRIM(B56),4)),VALUE(MID(TRIM(B56),4,2)),VALUE(LEFT(TRIM(B56),2))), DATEVALUE(TRIM(B56)))), ""CHECK"")"),46211.0) -> 46211 | R56: =IF(O56="CHECK","CHECK",TEXT(O56,"mmm")) -> Jul | S56: =IF(O56="CHECK","CHECK","Q"&INT((MONTH(O56)-1)/3)+1) -> Q3 | T56: =IFERROR(IF(G56="see notes",IF(ISNUMBER(VALUE(L56)),VALUE(L56),0),IF(G56="",0,IF(H56="GBP",VALUE(G56)*1.27,IF(AND(ISNUMBER(VALUE(G56)),F56="Revenue",VALUE(G56)<0),ABS(VALUE(G56)),IF(ISNUMBER(VALUE(G56)),VALUE(G56),0))))),0) -> 234800.48
A57: TXN-1134 | B57: Apr-24 | C57: Revenue | D57: Licensing | E57: SALES | F57: Licensing - ClearPath Finance | G57: 11239.35 | H57: USD | I57: James Okafor | J57: Apr | K57: Q2 | N57: =IFERROR(VLOOKUP(TRIM(E57),$P$2:$Q$23,2,FALSE),"UNMAPPED - CHECK") -> Sales | O57: =IFERROR(__xludf.DUMMYFUNCTION("IFERROR( IF(LEN(TRIM(B57))=6, DATE(2000+VALUE(RIGHT(TRIM(B57),2)),MATCH(LEFT(TRIM(B57),3),{""Jan"",""Feb"",""Mar"",""Apr"",""May"",""Jun"",""Jul"",""Aug"",""Sep"",""Oct"",""Nov"",""Dec""},0),15), IF(REGEXMATCH(TRIM(B57),""^\d{2}[/-]\d{2}[/-]\d{4}$"&"""), DATE(VALUE(RIGHT(TRIM(B57),4)),VALUE(MID(TRIM(B57),4,2)),VALUE(LEFT(TRIM(B57),2))), DATEVALUE(TRIM(B57)))), ""CHECK"")"),45397.0) -> 45397 | R57: =IF(O57="CHECK","CHECK",TEXT(O57,"mmm")) -> Apr | S57: =IF(O57="CHECK","CHECK","Q"&INT((MONTH(O57)-1)/3)+1) -> Q2 | T57: =IFERROR(IF(G57="see notes",IF(ISNUMBER(VALUE(L57)),VALUE(L57),0),IF(G57="",0,IF(H57="GBP",VALUE(G57)*1.27,IF(AND(ISNUMBER(VALUE(G57)),F57="Revenue",VALUE(G57)<0),ABS(VALUE(G57)),IF(ISNUMBER(VALUE(G57)),VALUE(G57),0))))),0) -> 11239.35
A58: TXN-1354 | B58: September 10, 2024 | C58: Revenue | D58: Professional Services | E58: SALES | F58: Professional Services - ClearPath Finance | G58: 13928.63 | H58: USD | I58: Daniel Müller | J58: Sep | K58: Q3 | N58: =IFERROR(VLOOKUP(TRIM(E58),$P$2:$Q$23,2,FALSE),"UNMAPPED - CHECK") -> Sales | O58: =IFERROR(__xludf.DUMMYFUNCTION("IFERROR( IF(LEN(TRIM(B58))=6, DATE(2000+VALUE(RIGHT(TRIM(B58),2)),MATCH(LEFT(TRIM(B58),3),{""Jan"",""Feb"",""Mar"",""Apr"",""May"",""Jun"",""Jul"",""Aug"",""Sep"",""Oct"",""Nov"",""Dec""},0),15), IF(REGEXMATCH(TRIM(B58),""^\d{2}[/-]\d{2}[/-]\d{4}$"&"""), DATE(VALUE(RIGHT(TRIM(B58),4)),VALUE(MID(TRIM(B58),4,2)),VALUE(LEFT(TRIM(B58),2))), DATEVALUE(TRIM(B58)))), ""CHECK"")"),45545.0) -> 45545 | R58: =IF(O58="CHECK","CHECK",TEXT(O58,"mmm")) -> Sep | S58: =IF(O58="CHECK","CHECK","Q"&INT((MONTH(O58)-1)/3)+1) -> Q3 | T58: =IFERROR(IF(G58="see notes",IF(ISNUMBER(VALUE(L58)),VALUE(L58),0),IF(G58="",0,IF(H58="GBP",VALUE(G58)*1.27,IF(AND(ISNUMBER(VALUE(G58)),F58="Revenue",VALUE(G58)<0),ABS(VALUE(G58)),IF(ISNUMBER(VALUE(G58)),VALUE(G58),0))))),0) -> 13928.63
A59: TXN-1128 | B59: 18/04/2024 | C59: Revenue | D59: Professional Services | E59: Sales | F59: Professional Services - Pinnacle Systems | G59: 50605.28 | H59: USD | I59: Priya Nair | J59: Apr | K59: Q2 | N59: =IFERROR(VLOOKUP(TRIM(E59),$P$2:$Q$23,2,FALSE),"UNMAPPED - CHECK") -> Sales | O59: =IFERROR(__xludf.DUMMYFUNCTION("IFERROR( IF(LEN(TRIM(B59))=6, DATE(2000+VALUE(RIGHT(TRIM(B59),2)),MATCH(LEFT(TRIM(B59),3),{""Jan"",""Feb"",""Mar"",""Apr"",""May"",""Jun"",""Jul"",""Aug"",""Sep"",""Oct"",""Nov"",""Dec""},0),15), IF(REGEXMATCH(TRIM(B59),""^\d{2}[/-]\d{2}[/-]\d{4}$"&"""), DATE(VALUE(RIGHT(TRIM(B59),4)),VALUE(MID(TRIM(B59),4,2)),VALUE(LEFT(TRIM(B59),2))), DATEVALUE(TRIM(B59)))), ""CHECK"")"),45400.0) -> 45400 | R59: =IF(O59="CHECK","CHECK",TEXT(O59,"mmm")) -> Apr | S59: =IF(O59="CHECK","CHECK","Q"&INT((MONTH(O59)-1)/3)+1) -> Q2 | T59: =IFERROR(IF(G59="see notes",IF(ISNUMBER(VALUE(L59)),VALUE(L59),0),IF(G59="",0,IF(H59="GBP",VALUE(G59)*1.27,IF(AND(ISNUMBER(VALUE(G59)),F59="Revenue",VALUE(G59)<0),ABS(VALUE(G59)),IF(ISNUMBER(VALUE(G59)),VALUE(G59),0))))),0) -> 50605.28
A60: TXN-1292 | B60: July 07, 2024 | C60: Expense | D60: Cloud Infrastructure | E60: Cloud Infra | F60: Software License - Google Cloud | G60: 35318.3 | H60: USD | I60: Google Cloud | J60: Jul | K60: Q3 | N60: =IFERROR(VLOOKUP(TRIM(E60),$P$2:$Q$23,2,FALSE),"UNMAPPED - CHECK") -> Cloud Infrastructure | O60: =IFERROR(__xludf.DUMMYFUNCTION("IFERROR( IF(LEN(TRIM(B60))=6, DATE(2000+VALUE(RIGHT(TRIM(B60),2)),MATCH(LEFT(TRIM(B60),3),{""Jan"",""Feb"",""Mar"",""Apr"",""May"",""Jun"",""Jul"",""Aug"",""Sep"",""Oct"",""Nov"",""Dec""},0),15), IF(REGEXMATCH(TRIM(B60),""^\d{2}[/-]\d{2}[/-]\d{4}$"&"""), DATE(VALUE(RIGHT(TRIM(B60),4)),VALUE(MID(TRIM(B60),4,2)),VALUE(LEFT(TRIM(B60),2))), DATEVALUE(TRIM(B60)))), ""CHECK"")"),45480.0) -> 45480 | R60: =IF(O60="CHECK","CHECK",TEXT(O60,"mmm")) -> Jul | S60: =IF(O60="CHECK","CHECK","Q"&INT((MONTH(O60)-1)/3)+1) -> Q3 | T60: =IFERROR(IF(G60="see notes",IF(ISNUMBER(VALUE(L60)),VALUE(L60),0),IF(G60="",0,IF(H60="GBP",VALUE(G60)*1.27,IF(AND(ISNUMBER(VALUE(G60)),F60="Revenue",VALUE(G60)<0),ABS(VALUE(G60)),IF(ISNUMBER(VALUE(G60)),VALUE(G60),0))))),0) -> 35318.3
A61: TXN-1357 | B61: Sep-24 | C61: Revenue | D61: Licensing | E61: Sales Dept | F61: Licensing - Redwood Partners | G61: 9224.9 | H61: USD | I61: Priya Nair | J61: Sep | K61: Q3 | N61: =IFERROR(VLOOKUP(TRIM(E61),$P$2:$Q$23,2,FALSE),"UNMAPPED - CHECK") -> Sales | O61: =IFERROR(__xludf.DUMMYFUNCTION("IFERROR( IF(LEN(TRIM(B61))=6, DATE(2000+VALUE(RIGHT(TRIM(B61),2)),MATCH(LEFT(TRIM(B61),3),{""Jan"",""Feb"",""Mar"",""Apr"",""May"",""Jun"",""Jul"",""Aug"",""Sep"",""Oct"",""Nov"",""Dec""},0),15), IF(REGEXMATCH(TRIM(B61),""^\d{2}[/-]\d{2}[/-]\d{4}$"&"""), DATE(VALUE(RIGHT(TRIM(B61),4)),VALUE(MID(TRIM(B61),4,2)),VALUE(LEFT(TRIM(B61),2))), DATEVALUE(TRIM(B61)))), ""CHECK"")"),45550.0) -> 45550 | R61: =IF(O61="CHECK","CHECK",TEXT(O61,"mmm")) -> Sep | S61: =IF(O61="CHECK","CHECK","Q"&INT((MONTH(O61)-1)/3)+1) -> Q3 | T61: =IFERROR(IF(G61="see notes",IF(ISNUMBER(VALUE(L61)),VALUE(L61),0),IF(G61="",0,IF(H61="GBP",VALUE(G61)*1.27,IF(AND(ISNUMBER(VALUE(G61)),F61="Revenue",VALUE(G61)<0),ABS(VALUE(G61)),IF(ISNUMBER(VALUE(G61)),VALUE(G61),0))))),0) -> 9224.9
A62: TXN-1456 | B62: 11/16/2024 | C62: Expense | D62: Marketing | E62: marketing | F62: PR Agency - WeWork | G62: 49650.39 | H62: USD | I62: WeWork | J62: Nov | K62: Q4 | N62: =IFERROR(VLOOKUP(TRIM(E62),$P$2:$Q$23,2,FALSE),"UNMAPPED - CHECK") -> Marketing | O62: =IFERROR(__xludf.DUMMYFUNCTION("IFERROR( IF(LEN(TRIM(B62))=6, DATE(2000+VALUE(RIGHT(TRIM(B62),2)),MATCH(LEFT(TRIM(B62),3),{""Jan"",""Feb"",""Mar"",""Apr"",""May"",""Jun"",""Jul"",""Aug"",""Sep"",""Oct"",""Nov"",""Dec""},0),15), IF(REGEXMATCH(TRIM(B62),""^\d{2}[/-]\d{2}[/-]\d{4}$"&"""), DATE(VALUE(RIGHT(TRIM(B62),4)),VALUE(MID(TRIM(B62),4,2)),VALUE(LEFT(TRIM(B62),2))), DATEVALUE(TRIM(B62)))), ""CHECK"")"),45758.0) -> 45758 | R62: =IF(O62="CHECK","CHECK",TEXT(O62,"mmm")) -> Apr | S62: =IF(O62="CHECK","CHECK","Q"&INT((MONTH(O62)-1)/3)+1) -> Q2 | T62: =IFERROR(IF(G62="see notes",IF(ISNUMBER(VALUE(L62)),VALUE(L62),0),IF(G62="",0,IF(H62="GBP",VALUE(G62)*1.27,IF(AND(ISNUMBER(VALUE(G62)),F62="Revenue",VALUE(G62)<0),ABS(VALUE(G62)),IF(ISNUMBER(VALUE(G62)),VALUE(G62),0))))),0) -> 49650.39
A63: TXN-1506 | B63: Dec-24 | C63: Expense | D63: Engineering | E63: Engineering | F63: PR Agency - Zoom | G63: 16137.19 | H63: USD | I63: Zoom | J63: Dec | K63: Q4 | N63: =IFERROR(VLOOKUP(TRIM(E63),$P$2:$Q$23,2,FALSE),"UNMAPPED - CHECK") -> Engineering | O63: =IFERROR(__xludf.DUMMYFUNCTION("IFERROR( IF(LEN(TRIM(B63))=6, DATE(2000+VALUE(RIGHT(TRIM(B63),2)),MATCH(LEFT(TRIM(B63),3),{""Jan"",""Feb"",""Mar"",""Apr"",""May"",""Jun"",""Jul"",""Aug"",""Sep"",""Oct"",""Nov"",""Dec""},0),15), IF(REGEXMATCH(TRIM(B63),""^\d{2}[/-]\d{2}[/-]\d{4}$"&"""), DATE(VALUE(RIGHT(TRIM(B63),4)),VALUE(MID(TRIM(B63),4,2)),VALUE(LEFT(TRIM(B63),2))), DATEVALUE(TRIM(B63)))), ""CHECK"")"),45641.0) -> 45641 | R63: =IF(O63="CHECK","CHECK",TEXT(O63,"mmm")) -> Dec | S63: =IF(O63="CHECK","CHECK","Q"&INT((MONTH(O63)-1)/3)+1) -> Q4 | T63: =IFERROR(IF(G63="see notes",IF(ISNUMBER(VALUE(L63)),VALUE(L63),0),IF(G63="",0,IF(H63="GBP",VALUE(G63)*1.27,IF(AND(ISNUMBER(VALUE(G63)),F63="Revenue",VALUE(G63)<0),ABS(VALUE(G63)),IF(ISNUMBER(VALUE(G63)),VALUE(G63),0))))),0) -> 16137.19
A64: TXN-1130 | B64: 2024-04-05 | C64: Revenue | D64: Licensing | E64: Sales | F64: Licensing - Pinnacle Systems | G64: 8576.04 | H64: USD | I64: Kwame Asante | J64: Apr | K64: Q2 | N64: =IFERROR(VLOOKUP(TRIM(E64),$P$2:$Q$23,2,FALSE),"UNMAPPED - CHECK") -> Sales | O64: =IFERROR(__xludf.DUMMYFUNCTION("IFERROR( IF(LEN(TRIM(B64))=6, DATE(2000+VALUE(RIGHT(TRIM(B64),2)),MATCH(LEFT(TRIM(B64),3),{""Jan"",""Feb"",""Mar"",""Apr"",""May"",""Jun"",""Jul"",""Aug"",""Sep"",""Oct"",""Nov"",""Dec""},0),15), IF(REGEXMATCH(TRIM(B64),""^\d{2}[/-]\d{2}[/-]\d{4}$"&"""), DATE(VALUE(RIGHT(TRIM(B64),4)),VALUE(MID(TRIM(B64),4,2)),VALUE(LEFT(TRIM(B64),2))), DATEVALUE(TRIM(B64)))), ""CHECK"")"),45387.0) -> 45387 | R64: =IF(O64="CHECK","CHECK",TEXT(O64,"mmm")) -> Apr | S64: =IF(O64="CHECK","CHECK","Q"&INT((MONTH(O64)-1)/3)+1) -> Q2 | T64: =IFERROR(IF(G64="see notes",IF(ISNUMBER(VALUE(L64)),VALUE(L64),0),IF(G64="",0,IF(H64="GBP",VALUE(G64)*1.27,IF(AND(ISNUMBER(VALUE(G64)),F64="Revenue",VALUE(G64)<0),ABS(VALUE(G64)),IF(ISNUMBER(VALUE(G64)),VALUE(G64),0))))),0) -> 8576.04
A65: TXN-1487 | B65: Dec-24 | C65: Revenue | D65: Licensing | E65: Sales | F65: Licensing - Pinnacle Systems | G65: 10361.24 | H65: USD | I65: Priya Nair | J65: Dec | K65: Q4 | N65: =IFERROR(VLOOKUP(TRIM(E65),$P$2:$Q$23,2,FALSE),"UNMAPPED - CHECK") -> Sales | O65: =IFERROR(__xludf.DUMMYFUNCTION("IFERROR( IF(LEN(TRIM(B65))=6, DATE(2000+VALUE(RIGHT(TRIM(B65),2)),MATCH(LEFT(TRIM(B65),3),{""Jan"",""Feb"",""Mar"",""Apr"",""May"",""Jun"",""Jul"",""Aug"",""Sep"",""Oct"",""Nov"",""Dec""},0),15), IF(REGEXMATCH(TRIM(B65),""^\d{2}[/-]\d{2}[/-]\d{4}$"&"""), DATE(VALUE(RIGHT(TRIM(B65),4)),VALUE(MID(TRIM(B65),4,2)),VALUE(LEFT(TRIM(B65),2))), DATEVALUE(TRIM(B65)))), ""CHECK"")"),45641.0) -> 45641 | R65: =IF(O65="CHECK","CHECK",TEXT(O65,"mmm")) -> Dec | S65: =IF(O65="CHECK","CHECK","Q"&INT((MONTH(O65)-1)/3)+1) -> Q4 | T65: =IFERROR(IF(G65="see notes",IF(ISNUMBER(VALUE(L65)),VALUE(L65),0),IF(G65="",0,IF(H65="GBP",VALUE(G65)*1.27,IF(AND(ISNUMBER(VALUE(G65)),F65="Revenue",VALUE(G65)<0),ABS(VALUE(G65)),IF(ISNUMBER(VALUE(G65)),VALUE(G65),0))))),0) -> 10361.24
A66: TXN-1188 | B66: 18/05/2024 | C66: Expense | D66: Engineering | E66: engineering | F66: Salary - Delta Airlines | G66: 38468.72 | H66: USD | I66: Delta Airlines | J66: May | K66: Q2 | N66: =IFERROR(VLOOKUP(TRIM(E66),$P$2:$Q$23,2,FALSE),"UNMAPPED - CHECK") -> Engineering | O66: =IFERROR(__xludf.DUMMYFUNCTION("IFERROR( IF(LEN(TRIM(B66))=6, DATE(2000+VALUE(RIGHT(TRIM(B66),2)),MATCH(LEFT(TRIM(B66),3),{""Jan"",""Feb"",""Mar"",""Apr"",""May"",""Jun"",""Jul"",""Aug"",""Sep"",""Oct"",""Nov"",""Dec""},0),15), IF(REGEXMATCH(TRIM(B66),""^\d{2}[/-]\d{2}[/-]\d{4}$"&"""), DATE(VALUE(RIGHT(TRIM(B66),4)),VALUE(MID(TRIM(B66),4,2)),VALUE(LEFT(TRIM(B66),2))), DATEVALUE(TRIM(B66)))), ""CHECK"")"),45430.0) -> 45430 | R66: =IF(O66="CHECK","CHECK",TEXT(O66,"mmm")) -> May | S66: =IF(O66="CHECK","CHECK","Q"&INT((MONTH(O66)-1)/3)+1) -> Q2 | T66: =IFERROR(IF(G66="see notes",IF(ISNUMBER(VALUE(L66)),VALUE(L66),0),IF(G66="",0,IF(H66="GBP",VALUE(G66)*1.27,IF(AND(ISNUMBER(VALUE(G66)),F66="Revenue",VALUE(G66)<0),ABS(VALUE(G66)),IF(ISNUMBER(VALUE(G66)),VALUE(G66),0))))),0) -> 38468.72
A67: TXN-1485 | B67: 12/29/2024 | C67: Revenue | D67: Professional Services | E67: Sales Dept | F67: Professional Services - Pinnacle Systems | G67: 12245.36 | H67: USD | I67: Kwame Asante | J67: Dec | K67: Q4 | N67: =IFERROR(VLOOKUP(TRIM(E67),$P$2:$Q$23,2,FALSE),"UNMAPPED - CHECK") -> Sales | O67: =IFERROR(__xludf.DUMMYFUNCTION("IFERROR( IF(LEN(TRIM(B67))=6, DATE(2000+VALUE(RIGHT(TRIM(B67),2)),MATCH(LEFT(TRIM(B67),3),{""Jan"",""Feb"",""Mar"",""Apr"",""May"",""Jun"",""Jul"",""Aug"",""Sep"",""Oct"",""Nov"",""Dec""},0),15), IF(REGEXMATCH(TRIM(B67),""^\d{2}[/-]\d{2}[/-]\d{4}$"&"""), DATE(VALUE(RIGHT(TRIM(B67),4)),VALUE(MID(TRIM(B67),4,2)),VALUE(LEFT(TRIM(B67),2))), DATEVALUE(TRIM(B67)))), ""CHECK"")"),46154.0) -> 46154 | R67: =IF(O67="CHECK","CHECK",TEXT(O67,"mmm")) -> May | S67: =IF(O67="CHECK","CHECK","Q"&INT((MONTH(O67)-1)/3)+1) -> Q2 | T67: =IFERROR(IF(G67="see notes",IF(ISNUMBER(VALUE(L67)),VALUE(L67),0),IF(G67="",0,IF(H67="GBP",VALUE(G67)*1.27,IF(AND(ISNUMBER(VALUE(G67)),F67="Revenue",VALUE(G67)<0),ABS(VALUE(G67)),IF(ISNUMBER(VALUE(G67)),VALUE(G67),0))))),0) -> 12245.36
A68: TXN-1264 | B68: 07/11/2024 | C68: Revenue | D68: Professional Services | E68: SALES | F68: Professional Services - Apex Retail | G68: 5237.29 | H68: USD | I68: Priya Nair | J68: Jul | K68: Q3 | N68: =IFERROR(VLOOKUP(TRIM(E68),$P$2:$Q$23,2,FALSE),"UNMAPPED - CHECK") -> Sales | O68: =IFERROR(__xludf.DUMMYFUNCTION("IFERROR( IF(LEN(TRIM(B68))=6, DATE(2000+VALUE(RIGHT(TRIM(B68),2)),MATCH(LEFT(TRIM(B68),3),{""Jan"",""Feb"",""Mar"",""Apr"",""May"",""Jun"",""Jul"",""Aug"",""Sep"",""Oct"",""Nov"",""Dec""},0),15), IF(REGEXMATCH(TRIM(B68),""^\d{2}[/-]\d{2}[/-]\d{4}$"&"""), DATE(VALUE(RIGHT(TRIM(B68),4)),VALUE(MID(TRIM(B68),4,2)),VALUE(LEFT(TRIM(B68),2))), DATEVALUE(TRIM(B68)))), ""CHECK"")"),45603.0) -> 45603 | R68: =IF(O68="CHECK","CHECK",TEXT(O68,"mmm")) -> Nov | S68: =IF(O68="CHECK","CHECK","Q"&INT((MONTH(O68)-1)/3)+1) -> Q4 | T68: =IFERROR(IF(G68="see notes",IF(ISNUMBER(VALUE(L68)),VALUE(L68),0),IF(G68="",0,IF(H68="GBP",VALUE(G68)*1.27,IF(AND(ISNUMBER(VALUE(G68)),F68="Revenue",VALUE(G68)<0),ABS(VALUE(G68)),IF(ISNUMBER(VALUE(G68)),VALUE(G68),0))))),0) -> 5237.29
A69: TXN-1390 | B69: 13-10-2024 | C69: Revenue | D69: Subscription | E69: SALES | F69: Subscription - Synapse AI | G69: 176379.84 | H69: USD | I69: Sofia Andersen | J69: Oct | K69: Q4 | N69: =IFERROR(VLOOKUP(TRIM(E69),$P$2:$Q$23,2,FALSE),"UNMAPPED - CHECK") -> Sales | O69: =IFERROR(__xludf.DUMMYFUNCTION("IFERROR( IF(LEN(TRIM(B69))=6, DATE(2000+VALUE(RIGHT(TRIM(B69),2)),MATCH(LEFT(TRIM(B69),3),{""Jan"",""Feb"",""Mar"",""Apr"",""May"",""Jun"",""Jul"",""Aug"",""Sep"",""Oct"",""Nov"",""Dec""},0),15), IF(REGEXMATCH(TRIM(B69),""^\d{2}[/-]\d{2}[/-]\d{4}$"&"""), DATE(VALUE(RIGHT(TRIM(B69),4)),VALUE(MID(TRIM(B69),4,2)),VALUE(LEFT(TRIM(B69),2))), DATEVALUE(TRIM(B69)))), ""CHECK"")"),45578.0) -> 45578 | R69: =IF(O69="CHECK","CHECK",TEXT(O69,"mmm")) -> Oct | S69: =IF(O69="CHECK","CHECK","Q"&INT((MONTH(O69)-1)/3)+1) -> Q4 | T69: =IFERROR(IF(G69="see notes",IF(ISNUMBER(VALUE(L69)),VALUE(L69),0),IF(G69="",0,IF(H69="GBP",VALUE(G69)*1.27,IF(AND(ISNUMBER(VALUE(G69)),F69="Revenue",VALUE(G69)<0),ABS(VALUE(G69)),IF(ISNUMBER(VALUE(G69)),VALUE(G69),0))))),0) -> 176379.84
A70: TXN-1203 | B70: 29/05/2024 | C70: Expense | D70: Cloud Infrastructure | E70: cloud infra | F70: AWS/Cloud - HubSpot | G70: 20825.33 | H70: USD | I70: HubSpot | J70: May | K70: Q2 | N70: =IFERROR(VLOOKUP(TRIM(E70),$P$2:$Q$23,2,FALSE),"UNMAPPED - CHECK") -> Cloud Infrastructure | O70: =IFERROR(__xludf.DUMMYFUNCTION("IFERROR( IF(LEN(TRIM(B70))=6, DATE(2000+VALUE(RIGHT(TRIM(B70),2)),MATCH(LEFT(TRIM(B70),3),{""Jan"",""Feb"",""Mar"",""Apr"",""May"",""Jun"",""Jul"",""Aug"",""Sep"",""Oct"",""Nov"",""Dec""},0),15), IF(REGEXMATCH(TRIM(B70),""^\d{2}[/-]\d{2}[/-]\d{4}$"&"""), DATE(VALUE(RIGHT(TRIM(B70),4)),VALUE(MID(TRIM(B70),4,2)),VALUE(LEFT(TRIM(B70),2))), DATEVALUE(TRIM(B70)))), ""CHECK"")"),45441.0) -> 45441 | R70: =IF(O70="CHECK","CHECK",TEXT(O70,"mmm")) -> May | S70: =IF(O70="CHECK","CHECK","Q"&INT((MONTH(O70)-1)/3)+1) -> Q2 | T70: =IFERROR(IF(G70="see notes",IF(ISNUMBER(VALUE(L70)),VALUE(L70),0),IF(G70="",0,IF(H70="GBP",VALUE(G70)*1.27,IF(AND(ISNUMBER(VALUE(G70)),F70="Revenue",VALUE(G70)<0),ABS(VALUE(G70)),IF(ISNUMBER(VALUE(G70)),VALUE(G70),0))))),0) -> 20825.33
A71: TXN-1216 | B71: 14-06-2024 | C71: Revenue | D71: Professional Services | E71: sales | F71: Professional Services - Orion Media | G71: 4920.56 | H71: USD | I71: Tom Bradley | J71: Jun | K71: Q2 | N71: =IFERROR(VLOOKUP(TRIM(E71),$P$2:$Q$23,2,FALSE),"UNMAPPED - CHECK") -> Sales | O71: =IFERROR(__xludf.DUMMYFUNCTION("IFERROR( IF(LEN(TRIM(B71))=6, DATE(2000+VALUE(RIGHT(TRIM(B71),2)),MATCH(LEFT(TRIM(B71),3),{""Jan"",""Feb"",""Mar"",""Apr"",""May"",""Jun"",""Jul"",""Aug"",""Sep"",""Oct"",""Nov"",""Dec""},0),15), IF(REGEXMATCH(TRIM(B71),""^\d{2}[/-]\d{2}[/-]\d{4}$"&"""), DATE(VALUE(RIGHT(TRIM(B71),4)),VALUE(MID(TRIM(B71),4,2)),VALUE(LEFT(TRIM(B71),2))), DATEVALUE(TRIM(B71)))), ""CHECK"")"),45457.0) -> 45457 | R71: =IF(O71="CHECK","CHECK",TEXT(O71,"mmm")) -> Jun | S71: =IF(O71="CHECK","CHECK","Q"&INT((MONTH(O71)-1)/3)+1) -> Q2 | T71: =IFERROR(IF(G71="see notes",IF(ISNUMBER(VALUE(L71)),VALUE(L71),0),IF(G71="",0,IF(H71="GBP",VALUE(G71)*1.27,IF(AND(ISNUMBER(VALUE(G71)),F71="Revenue",VALUE(G71)<0),ABS(VALUE(G71)),IF(ISNUMBER(VALUE(G71)),VALUE(G71),0))))),0) -> 4920.56
A72: TXN-1401 | B72: 21/10/2024 | C72: Revenue | D72: Licensing | E72: Sales Dept | F72: Licensing - Globex Corp | G72: 9013.03 | H72: USD | I72: James Okafor | J72: Oct | K72: Q4 | N72: =IFERROR(VLOOKUP(TRIM(E72),$P$2:$Q$23,2,FALSE),"UNMAPPED - CHECK") -> Sales | O72: =IFERROR(__xludf.DUMMYFUNCTION("IFERROR( IF(LEN(TRIM(B72))=6, DATE(2000+VALUE(RIGHT(TRIM(B72),2)),MATCH(LEFT(TRIM(B72),3),{""Jan"",""Feb"",""Mar"",""Apr"",""May"",""Jun"",""Jul"",""Aug"",""Sep"",""Oct"",""Nov"",""Dec""},0),15), IF(REGEXMATCH(TRIM(B72),""^\d{2}[/-]\d{2}[/-]\d{4}$"&"""), DATE(VALUE(RIGHT(TRIM(B72),4)),VALUE(MID(TRIM(B72),4,2)),VALUE(LEFT(TRIM(B72),2))), DATEVALUE(TRIM(B72)))), ""CHECK"")"),45586.0) -> 45586 | R72: =IF(O72="CHECK","CHECK",TEXT(O72,"mmm")) -> Oct | S72: =IF(O72="CHECK","CHECK","Q"&INT((MONTH(O72)-1)/3)+1) -> Q4 | T72: =IFERROR(IF(G72="see notes",IF(ISNUMBER(VALUE(L72)),VALUE(L72),0),IF(G72="",0,IF(H72="GBP",VALUE(G72)*1.27,IF(AND(ISNUMBER(VALUE(G72)),F72="Revenue",VALUE(G72)<0),ABS(VALUE(G72)),IF(ISNUMBER(VALUE(G72)),VALUE(G72),0))))),0) -> 9013.03
A73: TXN-1339 | B73: August 09, 2024 | C73: Expense | D73: G&A | E73: G&A | F73: Recruiting - Salesforce | G73: 12676.86 | H73: USD | I73: Salesforce | J73: Aug | K73: Q3 | N73: =IFERROR(VLOOKUP(TRIM(E73),$P$2:$Q$23,2,FALSE),"UNMAPPED - CHECK") -> G&A | O73: =IFERROR(__xludf.DUMMYFUNCTION("IFERROR( IF(LEN(TRIM(B73))=6, DATE(2000+VALUE(RIGHT(TRIM(B73),2)),MATCH(LEFT(TRIM(B73),3),{""Jan"",""Feb"",""Mar"",""Apr"",""May"",""Jun"",""Jul"",""Aug"",""Sep"",""Oct"",""Nov"",""Dec""},0),15), IF(REGEXMATCH(TRIM(B73),""^\d{2}[/-]\d{2}[/-]\d{4}$"&"""), DATE(VALUE(RIGHT(TRIM(B73),4)),VALUE(MID(TRIM(B73),4,2)),VALUE(LEFT(TRIM(B73),2))), DATEVALUE(TRIM(B73)))), ""CHECK"")"),45513.0) -> 45513 | R73: =IF(O73="CHECK","CHECK",TEXT(O73,"mmm")) -> Aug | S73: =IF(O73="CHECK","CHECK","Q"&INT((MONTH(O73)-1)/3)+1) -> Q3 | T73: =IFERROR(IF(G73="see notes",IF(ISNUMBER(VALUE(L73)),VALUE(L73),0),IF(G73="",0,IF(H73="GBP",VALUE(G73)*1.27,IF(AND(ISNUMBER(VALUE(G73)),F73="Revenue",VALUE(G73)<0),ABS(VALUE(G73)),IF(ISNUMBER(VALUE(G73)),VALUE(G73),0))))),0) -> 12676.86
A74: TXN-1116 | B74: 03/18/2024 | C74: Expense | D74: Cloud Infrastructure | E74: Cloud Infra | F74: Travel - Accenture | G74: 25409.61 | H74: USD | I74: Accenture | J74: Mar | K74: Q1 | N74: =IFERROR(VLOOKUP(TRIM(E74),$P$2:$Q$23,2,FALSE),"UNMAPPED - CHECK") -> Cloud Infrastructure | O74: =IFERROR(__xludf.DUMMYFUNCTION("IFERROR( IF(LEN(TRIM(B74))=6, DATE(2000+VALUE(RIGHT(TRIM(B74),2)),MATCH(LEFT(TRIM(B74),3),{""Jan"",""Feb"",""Mar"",""Apr"",""May"",""Jun"",""Jul"",""Aug"",""Sep"",""Oct"",""Nov"",""Dec""},0),15), IF(REGEXMATCH(TRIM(B74),""^\d{2}[/-]\d{2}[/-]\d{4}$"&"""), DATE(VALUE(RIGHT(TRIM(B74),4)),VALUE(MID(TRIM(B74),4,2)),VALUE(LEFT(TRIM(B74),2))), DATEVALUE(TRIM(B74)))), ""CHECK"")"),45811.0) -> 45811 | R74: =IF(O74="CHECK","CHECK",TEXT(O74,"mmm")) -> Jun | S74: =IF(O74="CHECK","CHECK","Q"&INT((MONTH(O74)-1)/3)+1) -> Q2 | T74: =IFERROR(IF(G74="see notes",IF(ISNUMBER(VALUE(L74)),VALUE(L74),0),IF(G74="",0,IF(H74="GBP",VALUE(G74)*1.27,IF(AND(ISNUMBER(VALUE(G74)),F74="Revenue",VALUE(G74)<0),ABS(VALUE(G74)),IF(ISNUMBER(VALUE(G74)),VALUE(G74),0))))),0) -> 25409.61
A75: TXN-1340 | B75: August 19, 2024 | C75: Expense | D75: G&A | E75: G & A | F75: Salary - HubSpot | G75: 16961.28 | H75: USD | I75: HubSpot | J75: Aug | K75: Q3 | N75: =IFERROR(VLOOKUP(TRIM(E75),$P$2:$Q$23,2,FALSE),"UNMAPPED - CHECK") -> G&A | O75: =IFERROR(__xludf.DUMMYFUNCTION("IFERROR( IF(LEN(TRIM(B75))=6, DATE(2000+VALUE(RIGHT(TRIM(B75),2)),MATCH(LEFT(TRIM(B75),3),{""Jan"",""Feb"",""Mar"",""Apr"",""May"",""Jun"",""Jul"",""Aug"",""Sep"",""Oct"",""Nov"",""Dec""},0),15), IF(REGEXMATCH(TRIM(B75),""^\d{2}[/-]\d{2}[/-]\d{4}$"&"""), DATE(VALUE(RIGHT(TRIM(B75),4)),VALUE(MID(TRIM(B75),4,2)),VALUE(LEFT(TRIM(B75),2))), DATEVALUE(TRIM(B75)))), ""CHECK"")"),45523.0) -> 45523 | R75: =IF(O75="CHECK","CHECK",TEXT(O75,"mmm")) -> Aug | S75: =IF(O75="CHECK","CHECK","Q"&INT((MONTH(O75)-1)/3)+1) -> Q3 | T75: =IFERROR(IF(G75="see notes",IF(ISNUMBER(VALUE(L75)),VALUE(L75),0),IF(G75="",0,IF(H75="GBP",VALUE(G75)*1.27,IF(AND(ISNUMBER(VALUE(G75)),F75="Revenue",VALUE(G75)<0),ABS(VALUE(G75)),IF(ISNUMBER(VALUE(G75)),VALUE(G75),0))))),0) -> 16961.28
A76: TXN-1185 | B76: May-24 | C76: Expense | D76: Marketing | E76: Mktng | F76: Ad Spend - Delta Airlines | G76: 56546.05 | H76: USD | I76: Delta Airlines | J76: May | K76: Q2 | N76: =IFERROR(VLOOKUP(TRIM(E76),$P$2:$Q$23,2,FALSE),"UNMAPPED - CHECK") -> Marketing | O76: =IFERROR(__xludf.DUMMYFUNCTION("IFERROR( IF(LEN(TRIM(B76))=6, DATE(2000+VALUE(RIGHT(TRIM(B76),2)),MATCH(LEFT(TRIM(B76),3),{""Jan"",""Feb"",""Mar"",""Apr"",""May"",""Jun"",""Jul"",""Aug"",""Sep"",""Oct"",""Nov"",""Dec""},0),15), IF(REGEXMATCH(TRIM(B76),""^\d{2}[/-]\d{2}[/-]\d{4}$"&"""), DATE(VALUE(RIGHT(TRIM(B76),4)),VALUE(MID(TRIM(B76),4,2)),VALUE(LEFT(TRIM(B76),2))), DATEVALUE(TRIM(B76)))), ""CHECK"")"),45427.0) -> 45427 | R76: =IF(O76="CHECK","CHECK",TEXT(O76,"mmm")) -> May | S76: =IF(O76="CHECK","CHECK","Q"&INT((MONTH(O76)-1)/3)+1) -> Q2 | T76: =IFERROR(IF(G76="see notes",IF(ISNUMBER(VALUE(L76)),VALUE(L76),0),IF(G76="",0,IF(H76="GBP",VALUE(G76)*1.27,IF(AND(ISNUMBER(VALUE(G76)),F76="Revenue",VALUE(G76)<0),ABS(VALUE(G76)),IF(ISNUMBER(VALUE(G76)),VALUE(G76),0))))),0) -> 56546.05
A77: TXN-1077 | B77: 02/27/2024 | C77: Expense | D77: Cloud Infrastructure | E77: Cloud Infra | F77: Contractor - Accenture | G77: 22073.81 | H77: USD | I77: Accenture | J77: Feb | K77: Q1 | N77: =IFERROR(VLOOKUP(TRIM(E77),$P$2:$Q$23,2,FALSE),"UNMAPPED - CHECK") -> Cloud Infrastructure | O77: =IFERROR(__xludf.DUMMYFUNCTION("IFERROR( IF(LEN(TRIM(B77))=6, DATE(2000+VALUE(RIGHT(TRIM(B77),2)),MATCH(LEFT(TRIM(B77),3),{""Jan"",""Feb"",""Mar"",""Apr"",""May"",""Jun"",""Jul"",""Aug"",""Sep"",""Oct"",""Nov"",""Dec""},0),15), IF(REGEXMATCH(TRIM(B77),""^\d{2}[/-]\d{2}[/-]\d{4}$"&"""), DATE(VALUE(RIGHT(TRIM(B77),4)),VALUE(MID(TRIM(B77),4,2)),VALUE(LEFT(TRIM(B77),2))), DATEVALUE(TRIM(B77)))), ""CHECK"")"),46083.0) -> 46083 | R77: =IF(O77="CHECK","CHECK",TEXT(O77,"mmm")) -> Mar | S77: =IF(O77="CHECK","CHECK","Q"&INT((MONTH(O77)-1)/3)+1) -> Q1 | T77: =IFERROR(IF(G77="see notes",IF(ISNUMBER(VALUE(L77)),VALUE(L77),0),IF(G77="",0,IF(H77="GBP",VALUE(G77)*1.27,IF(AND(ISNUMBER(VALUE(G77)),F77="Revenue",VALUE(G77)<0),ABS(VALUE(G77)),IF(ISNUMBER(VALUE(G77)),VALUE(G77),0))))),0) -> 22073.81
A78: TXN-1260 | B78: 09/07/2024 | C78: Revenue | D78: Professional Services | E78: sales | F78: Professional Services - Redwood Partners | G78: 19438.97 | H78: USD | I78: Tom Bradley | J78: Jul | K78: Q3 | N78: =IFERROR(VLOOKUP(TRIM(E78),$P$2:$Q$23,2,FALSE),"UNMAPPED - CHECK") -> Sales | O78: =IFERROR(__xludf.DUMMYFUNCTION("IFERROR( IF(LEN(TRIM(B78))=6, DATE(2000+VALUE(RIGHT(TRIM(B78),2)),MATCH(LEFT(TRIM(B78),3),{""Jan"",""Feb"",""Mar"",""Apr"",""May"",""Jun"",""Jul"",""Aug"",""Sep"",""Oct"",""Nov"",""Dec""},0),15), IF(REGEXMATCH(TRIM(B78),""^\d{2}[/-]\d{2}[/-]\d{4}$"&"""), DATE(VALUE(RIGHT(TRIM(B78),4)),VALUE(MID(TRIM(B78),4,2)),VALUE(LEFT(TRIM(B78),2))), DATEVALUE(TRIM(B78)))), ""CHECK"")"),45482.0) -> 45482 | R78: =IF(O78="CHECK","CHECK",TEXT(O78,"mmm")) -> Jul | S78: =IF(O78="CHECK","CHECK","Q"&INT((MONTH(O78)-1)/3)+1) -> Q3 | T78: =IFERROR(IF(G78="see notes",IF(ISNUMBER(VALUE(L78)),VALUE(L78),0),IF(G78="",0,IF(H78="GBP",VALUE(G78)*1.27,IF(AND(ISNUMBER(VALUE(G78)),F78="Revenue",VALUE(G78)<0),ABS(VALUE(G78)),IF(ISNUMBER(VALUE(G78)),VALUE(G78),0))))),0) -> 19438.97
A79: TXN-1099 | B79: Mar-24 | C79: Expense | D79: Marketing | E79: Marketing | F79: Contractor - Linklaters LLP | G79: 31905.83 | H79: USD | I79: Linklaters LLP | J79: Mar | K79: Q1 | N79: =IFERROR(VLOOKUP(TRIM(E79),$P$2:$Q$23,2,FALSE),"UNMAPPED - CHECK") -> Marketing | O79: =IFERROR(__xludf.DUMMYFUNCTION("IFERROR( IF(LEN(TRIM(B79))=6, DATE(2000+VALUE(RIGHT(TRIM(B79),2)),MATCH(LEFT(TRIM(B79),3),{""Jan"",""Feb"",""Mar"",""Apr"",""May"",""Jun"",""Jul"",""Aug"",""Sep"",""Oct"",""Nov"",""Dec""},0),15), IF(REGEXMATCH(TRIM(B79),""^\d{2}[/-]\d{2}[/-]\d{4}$"&"""), DATE(VALUE(RIGHT(TRIM(B79),4)),VALUE(MID(TRIM(B79),4,2)),VALUE(LEFT(TRIM(B79),2))), DATEVALUE(TRIM(B79)))), ""CHECK"")"),45366.0) -> 45366 | R79: =IF(O79="CHECK","CHECK",TEXT(O79,"mmm")) -> Mar | S79: =IF(O79="CHECK","CHECK","Q"&INT((MONTH(O79)-1)/3)+1) -> Q1 | T79: =IFERROR(IF(G79="see notes",IF(ISNUMBER(VALUE(L79)),VALUE(L79),0),IF(G79="",0,IF(H79="GBP",VALUE(G79)*1.27,IF(AND(ISNUMBER(VALUE(G79)),F79="Revenue",VALUE(G79)<0),ABS(VALUE(G79)),IF(ISNUMBER(VALUE(G79)),VALUE(G79),0))))),0) -> 31905.83
A80: TXN-1064 | B80: 22-02-2024 | C80: Expense | D80: Engineering | E80: R&D | F80: AWS/Cloud - HubSpot | G80: 14146.91 | H80: USD | I80: HubSpot | J80: Feb | K80: Q1 | N80: =IFERROR(VLOOKUP(TRIM(E80),$P$2:$Q$23,2,FALSE),"UNMAPPED - CHECK") -> Engineering | O80: =IFERROR(__xludf.DUMMYFUNCTION("IFERROR( IF(LEN(TRIM(B80))=6, DATE(2000+VALUE(RIGHT(TRIM(B80),2)),MATCH(LEFT(TRIM(B80),3),{""Jan"",""Feb"",""Mar"",""Apr"",""May"",""Jun"",""Jul"",""Aug"",""Sep"",""Oct"",""Nov"",""Dec""},0),15), IF(REGEXMATCH(TRIM(B80),""^\d{2}[/-]\d{2}[/-]\d{4}$"&"""), DATE(VALUE(RIGHT(TRIM(B80),4)),VALUE(MID(TRIM(B80),4,2)),VALUE(LEFT(TRIM(B80),2))), DATEVALUE(TRIM(B80)))), ""CHECK"")"),45344.0) -> 45344 | R80: =IF(O80="CHECK","CHECK",TEXT(O80,"mmm")) -> Feb | S80: =IF(O80="CHECK","CHECK","Q"&INT((MONTH(O80)-1)/3)+1) -> Q1 | T80: =IFERROR(IF(G80="see notes",IF(ISNUMBER(VALUE(L80)),VALUE(L80),0),IF(G80="",0,IF(H80="GBP",VALUE(G80)*1.27,IF(AND(ISNUMBER(VALUE(G80)),F80="Revenue",VALUE(G80)<0),ABS(VALUE(G80)),IF(ISNUMBER(VALUE(G80)),VALUE(G80),0))))),0) -> 14146.91
A81: TXN-1004 | B81: Jan-24 | C81: Revenue | D81: Professional Services | E81: Sales | F81: Professional Services - ClearPath Finance | G81: 11716.04 | H81: USD | I81: Priya Nair | J81: Jan | K81: Q1 | N81: =IFERROR(VLOOKUP(TRIM(E81),$P$2:$Q$23,2,FALSE),"UNMAPPED - CHECK") -> Sales | O81: =IFERROR(__xludf.DUMMYFUNCTION("IFERROR( IF(LEN(TRIM(B81))=6, DATE(2000+VALUE(RIGHT(TRIM(B81),2)),MATCH(LEFT(TRIM(B81),3),{""Jan"",""Feb"",""Mar"",""Apr"",""May"",""Jun"",""Jul"",""Aug"",""Sep"",""Oct"",""Nov"",""Dec""},0),15), IF(REGEXMATCH(TRIM(B81),""^\d{2}[/-]\d{2}[/-]\d{4}$"&"""), DATE(VALUE(RIGHT(TRIM(B81),4)),VALUE(MID(TRIM(B81),4,2)),VALUE(LEFT(TRIM(B81),2))), DATEVALUE(TRIM(B81)))), ""CHECK"")"),45306.0) -> 45306 | R81: =IF(O81="CHECK","CHECK",TEXT(O81,"mmm")) -> Jan | S81: =IF(O81="CHECK","CHECK","Q"&INT((MONTH(O81)-1)/3)+1) -> Q1 | T81: =IFERROR(IF(G81="see notes",IF(ISNUMBER(VALUE(L81)),VALUE(L81),0),IF(G81="",0,IF(H81="GBP",VALUE(G81)*1.27,IF(AND(ISNUMBER(VALUE(G81)),F81="Revenue",VALUE(G81)<0),ABS(VALUE(G81)),IF(ISNUMBER(VALUE(G81)),VALUE(G81),0))))),0) -> 11716.04
A82: TXN-1050 | B82: 29-02-2024 | C82: Revenue | D82: Licensing | E82: sales | F82: Licensing - Apex Retail | G82: 8582.78 | H82: USD | I82: Priya Nair | J82: Feb | K82: Q1 | N82: =IFERROR(VLOOKUP(TRIM(E82),$P$2:$Q$23,2,FALSE),"UNMAPPED - CHECK") -> Sales | O82: =IFERROR(__xludf.DUMMYFUNCTION("IFERROR( IF(LEN(TRIM(B82))=6, DATE(2000+VALUE(RIGHT(TRIM(B82),2)),MATCH(LEFT(TRIM(B82),3),{""Jan"",""Feb"",""Mar"",""Apr"",""May"",""Jun"",""Jul"",""Aug"",""Sep"",""Oct"",""Nov"",""Dec""},0),15), IF(REGEXMATCH(TRIM(B82),""^\d{2}[/-]\d{2}[/-]\d{4}$"&"""), DATE(VALUE(RIGHT(TRIM(B82),4)),VALUE(MID(TRIM(B82),4,2)),VALUE(LEFT(TRIM(B82),2))), DATEVALUE(TRIM(B82)))), ""CHECK"")"),45351.0) -> 45351 | R82: =IF(O82="CHECK","CHECK",TEXT(O82,"mmm")) -> Feb | S82: =IF(O82="CHECK","CHECK","Q"&INT((MONTH(O82)-1)/3)+1) -> Q1 | T82: =IFERROR(IF(G82="see notes",IF(ISNUMBER(VALUE(L82)),VALUE(L82),0),IF(G82="",0,IF(H82="GBP",VALUE(G82)*1.27,IF(AND(ISNUMBER(VALUE(G82)),F82="Revenue",VALUE(G82)<0),ABS(VALUE(G82)),IF(ISNUMBER(VALUE(G82)),VALUE(G82),0))))),0) -> 8582.78
A83: TXN-1418 | B83: Oct-24 | C83: Expense | D83: Customer Success | E83: Cust Success | F83: Recruiting - Google Cloud | G83: 19266.58 | H83: USD | I83: Google Cloud | J83: Oct | K83: Q4 | N83: =IFERROR(VLOOKUP(TRIM(E83),$P$2:$Q$23,2,FALSE),"UNMAPPED - CHECK") -> Customer Success | O83: =IFERROR(__xludf.DUMMYFUNCTION("IFERROR( IF(LEN(TRIM(B83))=6, DATE(2000+VALUE(RIGHT(TRIM(B83),2)),MATCH(LEFT(TRIM(B83),3),{""Jan"",""Feb"",""Mar"",""Apr"",""May"",""Jun"",""Jul"",""Aug"",""Sep"",""Oct"",""Nov"",""Dec""},0),15), IF(REGEXMATCH(TRIM(B83),""^\d{2}[/-]\d{2}[/-]\d{4}$"&"""), DATE(VALUE(RIGHT(TRIM(B83),4)),VALUE(MID(TRIM(B83),4,2)),VALUE(LEFT(TRIM(B83),2))), DATEVALUE(TRIM(B83)))), ""CHECK"")"),45580.0) -> 45580 | R83: =IF(O83="CHECK","CHECK",TEXT(O83,"mmm")) -> Oct | S83: =IF(O83="CHECK","CHECK","Q"&INT((MONTH(O83)-1)/3)+1) -> Q4 | T83: =IFERROR(IF(G83="see notes",IF(ISNUMBER(VALUE(L83)),VALUE(L83),0),IF(G83="",0,IF(H83="GBP",VALUE(G83)*1.27,IF(AND(ISNUMBER(VALUE(G83)),F83="Revenue",VALUE(G83)<0),ABS(VALUE(G83)),IF(ISNUMBER(VALUE(G83)),VALUE(G83),0))))),0) -> 19266.58
A84: TXN-1430 | B84: October 27, 2024 | C84: Expense | D84: Cloud Infrastructure | E84: Cloud Infrastructure | F84: Ad Spend - Hilton Hotels | G84: -18275.63 | H84: USD | I84: Hilton Hotels | J84: Oct | K84: Q4 | N84: =IFERROR(VLOOKUP(TRIM(E84),$P$2:$Q$23,2,FALSE),"UNMAPPED - CHECK") -> Cloud Infrastructure | O84: =IFERROR(__xludf.DUMMYFUNCTION("IFERROR( IF(LEN(TRIM(B84))=6, DATE(2000+VALUE(RIGHT(TRIM(B84),2)),MATCH(LEFT(TRIM(B84),3),{""Jan"",""Feb"",""Mar"",""Apr"",""May"",""Jun"",""Jul"",""Aug"",""Sep"",""Oct"",""Nov"",""Dec""},0),15), IF(REGEXMATCH(TRIM(B84),""^\d{2}[/-]\d{2}[/-]\d{4}$"&"""), DATE(VALUE(RIGHT(TRIM(B84),4)),VALUE(MID(TRIM(B84),4,2)),VALUE(LEFT(TRIM(B84),2))), DATEVALUE(TRIM(B84)))), ""CHECK"")"),45592.0) -> 45592 | R84: =IF(O84="CHECK","CHECK",TEXT(O84,"mmm")) -> Oct | S84: =IF(O84="CHECK","CHECK","Q"&INT((MONTH(O84)-1)/3)+1) -> Q4 | T84: =IFERROR(IF(G84="see notes",IF(ISNUMBER(VALUE(L84)),VALUE(L84),0),IF(G84="",0,IF(H84="GBP",VALUE(G84)*1.27,IF(AND(ISNUMBER(VALUE(G84)),F84="Revenue",VALUE(G84)<0),ABS(VALUE(G84)),IF(ISNUMBER(VALUE(G84)),VALUE(G84),0))))),0) -> -18275.63
A85: TXN-1396 | B85: 2024-10-01 | C85: Revenue | D85: Professional Services | E85: Sales Dept | F85: Professional Services - Redwood Partners | G85: 10631.4 | H85: USD | I85: James Okafor | J85: Oct | K85: Q4 | N85: =IFERROR(VLOOKUP(TRIM(E85),$P$2:$Q$23,2,FALSE),"UNMAPPED - CHECK") -> Sales | O85: =IFERROR(__xludf.DUMMYFUNCTION("IFERROR( IF(LEN(TRIM(B85))=6, DATE(2000+VALUE(RIGHT(TRIM(B85),2)),MATCH(LEFT(TRIM(B85),3),{""Jan"",""Feb"",""Mar"",""Apr"",""May"",""Jun"",""Jul"",""Aug"",""Sep"",""Oct"",""Nov"",""Dec""},0),15), IF(REGEXMATCH(TRIM(B85),""^\d{2}[/-]\d{2}[/-]\d{4}$"&"""), DATE(VALUE(RIGHT(TRIM(B85),4)),VALUE(MID(TRIM(B85),4,2)),VALUE(LEFT(TRIM(B85),2))), DATEVALUE(TRIM(B85)))), ""CHECK"")"),45566.0) -> 45566 | R85: =IF(O85="CHECK","CHECK",TEXT(O85,"mmm")) -> Oct | S85: =IF(O85="CHECK","CHECK","Q"&INT((MONTH(O85)-1)/3)+1) -> Q4 | T85: =IFERROR(IF(G85="see notes",IF(ISNUMBER(VALUE(L85)),VALUE(L85),0),IF(G85="",0,IF(H85="GBP",VALUE(G85)*1.27,IF(AND(ISNUMBER(VALUE(G85)),F85="Revenue",VALUE(G85)<0),ABS(VALUE(G85)),IF(ISNUMBER(VALUE(G85)),VALUE(G85),0))))),0) -> 10631.4
A86: TXN-1287 | B86: 03/07/2024 | C86: Expense | D86: G&A | E86: General & Admin | F86: AWS/Cloud - HubSpot | G86: 8050.17 | H86: USD | I86: HubSpot | J86: Jul | K86: Q3 | N86: =IFERROR(VLOOKUP(TRIM(E86),$P$2:$Q$23,2,FALSE),"UNMAPPED - CHECK") -> G&A | O86: =IFERROR(__xludf.DUMMYFUNCTION("IFERROR( IF(LEN(TRIM(B86))=6, DATE(2000+VALUE(RIGHT(TRIM(B86),2)),MATCH(LEFT(TRIM(B86),3),{""Jan"",""Feb"",""Mar"",""Apr"",""May"",""Jun"",""Jul"",""Aug"",""Sep"",""Oct"",""Nov"",""Dec""},0),15), IF(REGEXMATCH(TRIM(B86),""^\d{2}[/-]\d{2}[/-]\d{4}$"&"""), DATE(VALUE(RIGHT(TRIM(B86),4)),VALUE(MID(TRIM(B86),4,2)),VALUE(LEFT(TRIM(B86),2))), DATEVALUE(TRIM(B86)))), ""CHECK"")"),45476.0) -> 45476 | R86: =IF(O86="CHECK","CHECK",TEXT(O86,"mmm")) -> Jul | S86: =IF(O86="CHECK","CHECK","Q"&INT((MONTH(O86)-1)/3)+1) -> Q3 | T86: =IFERROR(IF(G86="see notes",IF(ISNUMBER(VALUE(L86)),VALUE(L86),0),IF(G86="",0,IF(H86="GBP",VALUE(G86)*1.27,IF(AND(ISNUMBER(VALUE(G86)),F86="Revenue",VALUE(G86)<0),ABS(VALUE(G86)),IF(ISNUMBER(VALUE(G86)),VALUE(G86),0))))),0) -> 8050.17
A87: TXN-1073 | B87: 26/02/2024 | C87: Expense | D87: Cloud Infrastructure | E87: CLOUD | F87: AWS/Cloud - Linklaters LLP | G87: 15849.2 | H87: USD | I87: Linklaters LLP | J87: Feb | K87: Q1 | N87: =IFERROR(VLOOKUP(TRIM(E87),$P$2:$Q$23,2,FALSE),"UNMAPPED - CHECK") -> Cloud Infrastructure | O87: =IFERROR(__xludf.DUMMYFUNCTION("IFERROR( IF(LEN(TRIM(B87))=6, DATE(2000+VALUE(RIGHT(TRIM(B87),2)),MATCH(LEFT(TRIM(B87),3),{""Jan"",""Feb"",""Mar"",""Apr"",""May"",""Jun"",""Jul"",""Aug"",""Sep"",""Oct"",""Nov"",""Dec""},0),15), IF(REGEXMATCH(TRIM(B87),""^\d{2}[/-]\d{2}[/-]\d{4}$"&"""), DATE(VALUE(RIGHT(TRIM(B87),4)),VALUE(MID(TRIM(B87),4,2)),VALUE(LEFT(TRIM(B87),2))), DATEVALUE(TRIM(B87)))), ""CHECK"")"),45348.0) -> 45348 | R87: =IF(O87="CHECK","CHECK",TEXT(O87,"mmm")) -> Feb | S87: =IF(O87="CHECK","CHECK","Q"&INT((MONTH(O87)-1)/3)+1) -> Q1 | T87: =IFERROR(IF(G87="see notes",IF(ISNUMBER(VALUE(L87)),VALUE(L87),0),IF(G87="",0,IF(H87="GBP",VALUE(G87)*1.27,IF(AND(ISNUMBER(VALUE(G87)),F87="Revenue",VALUE(G87)<0),ABS(VALUE(G87)),IF(ISNUMBER(VALUE(G87)),VALUE(G87),0))))),0) -> 15849.2
A88: TXN-1397 | B88: 2024-10-01 | C88: Revenue | D88: Professional Services | E88: SALES | F88: Professional Services - Redwood Partners | G88: 19724.98 | H88: USD | I88: Kwame Asante | J88: Oct | K88: Q4 | N88: =IFERROR(VLOOKUP(TRIM(E88),$P$2:$Q$23,2,FALSE),"UNMAPPED - CHECK") -> Sales | O88: =IFERROR(__xludf.DUMMYFUNCTION("IFERROR( IF(LEN(TRIM(B88))=6, DATE(2000+VALUE(RIGHT(TRIM(B88),2)),MATCH(LEFT(TRIM(B88),3),{""Jan"",""Feb"",""Mar"",""Apr"",""May"",""Jun"",""Jul"",""Aug"",""Sep"",""Oct"",""Nov"",""Dec""},0),15), IF(REGEXMATCH(TRIM(B88),""^\d{2}[/-]\d{2}[/-]\d{4}$"&"""), DATE(VALUE(RIGHT(TRIM(B88),4)),VALUE(MID(TRIM(B88),4,2)),VALUE(LEFT(TRIM(B88),2))), DATEVALUE(TRIM(B88)))), ""CHECK"")"),45566.0) -> 45566 | R88: =IF(O88="CHECK","CHECK",TEXT(O88,"mmm")) -> Oct | S88: =IF(O88="CHECK","CHECK","Q"&INT((MONTH(O88)-1)/3)+1) -> Q4 | T88: =IFERROR(IF(G88="see notes",IF(ISNUMBER(VALUE(L88)),VALUE(L88),0),IF(G88="",0,IF(H88="GBP",VALUE(G88)*1.27,IF(AND(ISNUMBER(VALUE(G88)),F88="Revenue",VALUE(G88)<0),ABS(VALUE(G88)),IF(ISNUMBER(VALUE(G88)),VALUE(G88),0))))),0) -> 19724.98
A89: TXN-1215 | B89: 21/06/2024 | C89: Revenue | D89: Professional Services | E89: sales | F89: Professional Services - Globex Corp | G89: 21169.37 | H89: USD | I89: James Okafor | J89: Jun | K89: Q2 | N89: =IFERROR(VLOOKUP(TRIM(E89),$P$2:$Q$23,2,FALSE),"UNMAPPED - CHECK") -> Sales | O89: =IFERROR(__xludf.DUMMYFUNCTION("IFERROR( IF(LEN(TRIM(B89))=6, DATE(2000+VALUE(RIGHT(TRIM(B89),2)),MATCH(LEFT(TRIM(B89),3),{""Jan"",""Feb"",""Mar"",""Apr"",""May"",""Jun"",""Jul"",""Aug"",""Sep"",""Oct"",""Nov"",""Dec""},0),15), IF(REGEXMATCH(TRIM(B89),""^\d{2}[/-]\d{2}[/-]\d{4}$"&"""), DATE(VALUE(RIGHT(TRIM(B89),4)),VALUE(MID(TRIM(B89),4,2)),VALUE(LEFT(TRIM(B89),2))), DATEVALUE(TRIM(B89)))), ""CHECK"")"),45464.0) -> 45464 | R89: =IF(O89="CHECK","CHECK",TEXT(O89,"mmm")) -> Jun | S89: =IF(O89="CHECK","CHECK","Q"&INT((MONTH(O89)-1)/3)+1) -> Q2 | T89: =IFERROR(IF(G89="see notes",IF(ISNUMBER(VALUE(L89)),VALUE(L89),0),IF(G89="",0,IF(H89="GBP",VALUE(G89)*1.27,IF(AND(ISNUMBER(VALUE(G89)),F89="Revenue",VALUE(G89)<0),ABS(VALUE(G89)),IF(ISNUMBER(VALUE(G89)),VALUE(G89),0))))),0) -> 21169.37
A90: TXN-1068 | B90: 01/02/2024 | C90: Expense | D90: G&A | E90: G & A | F90: AWS/Cloud - Omnicom Group | G90: 17700.94 | H90: USD | I90: Omnicom Group | J90: Feb | K90: Q1 | N90: =IFERROR(VLOOKUP(TRIM(E90),$P$2:$Q$23,2,FALSE),"UNMAPPED - CHECK") -> G&A | O90: =IFERROR(__xludf.DUMMYFUNCTION("IFERROR( IF(LEN(TRIM(B90))=6, DATE(2000+VALUE(RIGHT(TRIM(B90),2)),MATCH(LEFT(TRIM(B90),3),{""Jan"",""Feb"",""Mar"",""Apr"",""May"",""Jun"",""Jul"",""Aug"",""Sep"",""Oct"",""Nov"",""Dec""},0),15), IF(REGEXMATCH(TRIM(B90),""^\d{2}[/-]\d{2}[/-]\d{4}$"&"""), DATE(VALUE(RIGHT(TRIM(B90),4)),VALUE(MID(TRIM(B90),4,2)),VALUE(LEFT(TRIM(B90),2))), DATEVALUE(TRIM(B90)))), ""CHECK"")"),45323.0) -> 45323 | R90: =IF(O90="CHECK","CHECK",TEXT(O90,"mmm")) -> Feb | S90: =IF(O90="CHECK","CHECK","Q"&INT((MONTH(O90)-1)/3)+1) -> Q1 | T90: =IFERROR(IF(G90="see notes",IF(ISNUMBER(VALUE(L90)),VALUE(L90),0),IF(G90="",0,IF(H90="GBP",VALUE(G90)*1.27,IF(AND(ISNUMBER(VALUE(G90)),F90="Revenue",VALUE(G90)<0),ABS(VALUE(G90)),IF(ISNUMBER(VALUE(G90)),VALUE(G90),0))))),0) -> 17700.94
A91: TXN-1336 | B91: 02/08/2024 | C91: Expense | D91: G&A | E91: G&A | F91: AWS/Cloud - Slack | G91: 8503.75 | H91: USD | I91: Slack | J91: Aug | K91: Q3 | N91: =IFERROR(VLOOKUP(TRIM(E91),$P$2:$Q$23,2,FALSE),"UNMAPPED - CHECK") -> G&A | O91: =IFERROR(__xludf.DUMMYFUNCTION("IFERROR( IF(LEN(TRIM(B91))=6, DATE(2000+VALUE(RIGHT(TRIM(B91),2)),MATCH(LEFT(TRIM(B91),3),{""Jan"",""Feb"",""Mar"",""Apr"",""May"",""Jun"",""Jul"",""Aug"",""Sep"",""Oct"",""Nov"",""Dec""},0),15), IF(REGEXMATCH(TRIM(B91),""^\d{2}[/-]\d{2}[/-]\d{4}$"&"""), DATE(VALUE(RIGHT(TRIM(B91),4)),VALUE(MID(TRIM(B91),4,2)),VALUE(LEFT(TRIM(B91),2))), DATEVALUE(TRIM(B91)))), ""CHECK"")"),45506.0) -> 45506 | R91: =IF(O91="CHECK","CHECK",TEXT(O91,"mmm")) -> Aug | S91: =IF(O91="CHECK","CHECK","Q"&INT((MONTH(O91)-1)/3)+1) -> Q3 | T91: =IFERROR(IF(G91="see notes",IF(ISNUMBER(VALUE(L91)),VALUE(L91),0),IF(G91="",0,IF(H91="GBP",VALUE(G91)*1.27,IF(AND(ISNUMBER(VALUE(G91)),F91="Revenue",VALUE(G91)<0),ABS(VALUE(G91)),IF(ISNUMBER(VALUE(G91)),VALUE(G91),0))))),0) -> 8503.75
A92: TXN-1233 | B92: Jun-24 | C92: Expense | D92: Engineering | E92: R&D | F92: PR Agency - Delta Airlines | G92: 23569.5 | H92: USD | I92: Delta Airlines | J92: Jun | K92: Q2 | N92: =IFERROR(VLOOKUP(TRIM(E92),$P$2:$Q$23,2,FALSE),"UNMAPPED - CHECK") -> Engineering | O92: =IFERROR(__xludf.DUMMYFUNCTION("IFERROR( IF(LEN(TRIM(B92))=6, DATE(2000+VALUE(RIGHT(TRIM(B92),2)),MATCH(LEFT(TRIM(B92),3),{""Jan"",""Feb"",""Mar"",""Apr"",""May"",""Jun"",""Jul"",""Aug"",""Sep"",""Oct"",""Nov"",""Dec""},0),15), IF(REGEXMATCH(TRIM(B92),""^\d{2}[/-]\d{2}[/-]\d{4}$"&"""), DATE(VALUE(RIGHT(TRIM(B92),4)),VALUE(MID(TRIM(B92),4,2)),VALUE(LEFT(TRIM(B92),2))), DATEVALUE(TRIM(B92)))), ""CHECK"")"),45458.0) -> 45458 | R92: =IF(O92="CHECK","CHECK",TEXT(O92,"mmm")) -> Jun | S92: =IF(O92="CHECK","CHECK","Q"&INT((MONTH(O92)-1)/3)+1) -> Q2 | T92: =IFERROR(IF(G92="see notes",IF(ISNUMBER(VALUE(L92)),VALUE(L92),0),IF(G92="",0,IF(H92="GBP",VALUE(G92)*1.27,IF(AND(ISNUMBER(VALUE(G92)),F92="Revenue",VALUE(G92)<0),ABS(VALUE(G92)),IF(ISNUMBER(VALUE(G92)),VALUE(G92),0))))),0) -> 23569.5
A93: TXN-1312 | B93: 25/08/2024 | C93: Revenue | D93: Licensing | E93: Sales Dept | F93: Licensing - Synapse AI | G93: 5011.51 | H93: USD | I93: Daniel Müller | J93: Aug | K93: Q3 | N93: =IFERROR(VLOOKUP(TRIM(E93),$P$2:$Q$23,2,FALSE),"UNMAPPED - CHECK") -> Sales | O93: =IFERROR(__xludf.DUMMYFUNCTION("IFERROR( IF(LEN(TRIM(B93))=6, DATE(2000+VALUE(RIGHT(TRIM(B93),2)),MATCH(LEFT(TRIM(B93),3),{""Jan"",""Feb"",""Mar"",""Apr"",""May"",""Jun"",""Jul"",""Aug"",""Sep"",""Oct"",""Nov"",""Dec""},0),15), IF(REGEXMATCH(TRIM(B93),""^\d{2}[/-]\d{2}[/-]\d{4}$"&"""), DATE(VALUE(RIGHT(TRIM(B93),4)),VALUE(MID(TRIM(B93),4,2)),VALUE(LEFT(TRIM(B93),2))), DATEVALUE(TRIM(B93)))), ""CHECK"")"),45529.0) -> 45529 | R93: =IF(O93="CHECK","CHECK",TEXT(O93,"mmm")) -> Aug | S93: =IF(O93="CHECK","CHECK","Q"&INT((MONTH(O93)-1)/3)+1) -> Q3 | T93: =IFERROR(IF(G93="see notes",IF(ISNUMBER(VALUE(L93)),VALUE(L93),0),IF(G93="",0,IF(H93="GBP",VALUE(G93)*1.27,IF(AND(ISNUMBER(VALUE(G93)),F93="Revenue",VALUE(G93)<0),ABS(VALUE(G93)),IF(ISNUMBER(VALUE(G93)),VALUE(G93),0))))),0) -> 5011.51
A94: TXN-1475 | B94: Nov-24 | C94: Expense | D94: Cloud Infrastructure | E94: Cloud | F94: AWS/Cloud - Zoom | G94: 33462.21 | H94: USD | I94: Zoom | J94: Nov | K94: Q4 | N94: =IFERROR(VLOOKUP(TRIM(E94),$P$2:$Q$23,2,FALSE),"UNMAPPED - CHECK") -> Cloud Infrastructure | O94: =IFERROR(__xludf.DUMMYFUNCTION("IFERROR( IF(LEN(TRIM(B94))=6, DATE(2000+VALUE(RIGHT(TRIM(B94),2)),MATCH(LEFT(TRIM(B94),3),{""Jan"",""Feb"",""Mar"",""Apr"",""May"",""Jun"",""Jul"",""Aug"",""Sep"",""Oct"",""Nov"",""Dec""},0),15), IF(REGEXMATCH(TRIM(B94),""^\d{2}[/-]\d{2}[/-]\d{4}$"&"""), DATE(VALUE(RIGHT(TRIM(B94),4)),VALUE(MID(TRIM(B94),4,2)),VALUE(LEFT(TRIM(B94),2))), DATEVALUE(TRIM(B94)))), ""CHECK"")"),45611.0) -> 45611 | R94: =IF(O94="CHECK","CHECK",TEXT(O94,"mmm")) -> Nov | S94: =IF(O94="CHECK","CHECK","Q"&INT((MONTH(O94)-1)/3)+1) -> Q4 | T94: =IFERROR(IF(G94="see notes",IF(ISNUMBER(VALUE(L94)),VALUE(L94),0),IF(G94="",0,IF(H94="GBP",VALUE(G94)*1.27,IF(AND(ISNUMBER(VALUE(G94)),F94="Revenue",VALUE(G94)<0),ABS(VALUE(G94)),IF(ISNUMBER(VALUE(G94)),VALUE(G94),0))))),0) -> 33462.21
A95: TXN-1365 | B95: 29/09/2024 | C95: Expense | D95: Marketing | E95: marketing | F95: Ad Spend - WeWork | G95: 31653.81 | H95: USD | I95: WeWork | J95: Sep | K95: Q3 | N95: =IFERROR(VLOOKUP(TRIM(E95),$P$2:$Q$23,2,FALSE),"UNMAPPED - CHECK") -> Marketing | O95: =IFERROR(__xludf.DUMMYFUNCTION("IFERROR( IF(LEN(TRIM(B95))=6, DATE(2000+VALUE(RIGHT(TRIM(B95),2)),MATCH(LEFT(TRIM(B95),3),{""Jan"",""Feb"",""Mar"",""Apr"",""May"",""Jun"",""Jul"",""Aug"",""Sep"",""Oct"",""Nov"",""Dec""},0),15), IF(REGEXMATCH(TRIM(B95),""^\d{2}[/-]\d{2}[/-]\d{4}$"&"""), DATE(VALUE(RIGHT(TRIM(B95),4)),VALUE(MID(TRIM(B95),4,2)),VALUE(LEFT(TRIM(B95),2))), DATEVALUE(TRIM(B95)))), ""CHECK"")"),45564.0) -> 45564 | R95: =IF(O95="CHECK","CHECK",TEXT(O95,"mmm")) -> Sep | S95: =IF(O95="CHECK","CHECK","Q"&INT((MONTH(O95)-1)/3)+1) -> Q3 | T95: =IFERROR(IF(G95="see notes",IF(ISNUMBER(VALUE(L95)),VALUE(L95),0),IF(G95="",0,IF(H95="GBP",VALUE(G95)*1.27,IF(AND(ISNUMBER(VALUE(G95)),F95="Revenue",VALUE(G95)<0),ABS(VALUE(G95)),IF(ISNUMBER(VALUE(G95)),VALUE(G95),0))))),0) -> 31653.81
A96: TXN-1412 | B96: 10/21/2024 | C96: Expense | D96: Marketing | E96: marketing | F96: PR Agency - Slack | G96: 50426.49 | H96: USD | I96: Slack | J96: Oct | K96: Q4 | N96: =IFERROR(VLOOKUP(TRIM(E96),$P$2:$Q$23,2,FALSE),"UNMAPPED - CHECK") -> Marketing | O96: =IFERROR(__xludf.DUMMYFUNCTION("IFERROR( IF(LEN(TRIM(B96))=6, DATE(2000+VALUE(RIGHT(TRIM(B96),2)),MATCH(LEFT(TRIM(B96),3),{""Jan"",""Feb"",""Mar"",""Apr"",""May"",""Jun"",""Jul"",""Aug"",""Sep"",""Oct"",""Nov"",""Dec""},0),15), IF(REGEXMATCH(TRIM(B96),""^\d{2}[/-]\d{2}[/-]\d{4}$"&"""), DATE(VALUE(RIGHT(TRIM(B96),4)),VALUE(MID(TRIM(B96),4,2)),VALUE(LEFT(TRIM(B96),2))), DATEVALUE(TRIM(B96)))), ""CHECK"")"),45910.0) -> 45910 | R96: =IF(O96="CHECK","CHECK",TEXT(O96,"mmm")) -> Sep | S96: =IF(O96="CHECK","CHECK","Q"&INT((MONTH(O96)-1)/3)+1) -> Q3 | T96: =IFERROR(IF(G96="see notes",IF(ISNUMBER(VALUE(L96)),VALUE(L96),0),IF(G96="",0,IF(H96="GBP",VALUE(G96)*1.27,IF(AND(ISNUMBER(VALUE(G96)),F96="Revenue",VALUE(G96)<0),ABS(VALUE(G96)),IF(ISNUMBER(VALUE(G96)),VALUE(G96),0))))),0) -> 50426.49
A97: TXN-1142 | B97: 2024-04-28 | C97: Expense | D97: Marketing | E97: marketing | F97: Ad Spend - Omnicom Group | G97: 74351.66 | H97: USD | I97: Omnicom Group | J97: Apr | K97: Q2 | N97: =IFERROR(VLOOKUP(TRIM(E97),$P$2:$Q$23,2,FALSE),"UNMAPPED - CHECK") -> Marketing | O97: =IFERROR(__xludf.DUMMYFUNCTION("IFERROR( IF(LEN(TRIM(B97))=6, DATE(2000+VALUE(RIGHT(TRIM(B97),2)),MATCH(LEFT(TRIM(B97),3),{""Jan"",""Feb"",""Mar"",""Apr"",""May"",""Jun"",""Jul"",""Aug"",""Sep"",""Oct"",""Nov"",""Dec""},0),15), IF(REGEXMATCH(TRIM(B97),""^\d{2}[/-]\d{2}[/-]\d{4}$"&"""), DATE(VALUE(RIGHT(TRIM(B97),4)),VALUE(MID(TRIM(B97),4,2)),VALUE(LEFT(TRIM(B97),2))), DATEVALUE(TRIM(B97)))), ""CHECK"")"),45410.0) -> 45410 | R97: =IF(O97="CHECK","CHECK",TEXT(O97,"mmm")) -> Apr | S97: =IF(O97="CHECK","CHECK","Q"&INT((MONTH(O97)-1)/3)+1) -> Q2 | T97: =IFERROR(IF(G97="see notes",IF(ISNUMBER(VALUE(L97)),VALUE(L97),0),IF(G97="",0,IF(H97="GBP",VALUE(G97)*1.27,IF(AND(ISNUMBER(VALUE(G97)),F97="Revenue",VALUE(G97)<0),ABS(VALUE(G97)),IF(ISNUMBER(VALUE(G97)),VALUE(G97),0))))),0) -> 74351.66
A98: TXN-1137 | B98: Apr-24 | C98: Expense | D98: Sales | E98: SALES | F98: Office Supplies - Randstad | G98: 28776.79 | H98: USD | I98: Randstad | J98: Apr | K98: Q2 | N98: =IFERROR(VLOOKUP(TRIM(E98),$P$2:$Q$23,2,FALSE),"UNMAPPED - CHECK") -> Sales | O98: =IFERROR(__xludf.DUMMYFUNCTION("IFERROR( IF(LEN(TRIM(B98))=6, DATE(2000+VALUE(RIGHT(TRIM(B98),2)),MATCH(LEFT(TRIM(B98),3),{""Jan"",""Feb"",""Mar"",""Apr"",""May"",""Jun"",""Jul"",""Aug"",""Sep"",""Oct"",""Nov"",""Dec""},0),15), IF(REGEXMATCH(TRIM(B98),""^\d{2}[/-]\d{2}[/-]\d{4}$"&"""), DATE(VALUE(RIGHT(TRIM(B98),4)),VALUE(MID(TRIM(B98),4,2)),VALUE(LEFT(TRIM(B98),2))), DATEVALUE(TRIM(B98)))), ""CHECK"")"),45397.0) -> 45397 | R98: =IF(O98="CHECK","CHECK",TEXT(O98,"mmm")) -> Apr | S98: =IF(O98="CHECK","CHECK","Q"&INT((MONTH(O98)-1)/3)+1) -> Q2 | T98: =IFERROR(IF(G98="see notes",IF(ISNUMBER(VALUE(L98)),VALUE(L98),0),IF(G98="",0,IF(H98="GBP",VALUE(G98)*1.27,IF(AND(ISNUMBER(VALUE(G98)),F98="Revenue",VALUE(G98)<0),ABS(VALUE(G98)),IF(ISNUMBER(VALUE(G98)),VALUE(G98),0))))),0) -> 28776.79
A99: TXN-1124 | B99: 25-04-2024 | C99: Revenue | D99: Professional Services | E99: Sales Dept | F99: Professional Services - Synapse AI | G99: 27844.39 | H99: USD | I99: Aisha Rahman | J99: Apr | K99: Q2 | N99: =IFERROR(VLOOKUP(TRIM(E99),$P$2:$Q$23,2,FALSE),"UNMAPPED - CHECK") -> Sales | O99: =IFERROR(__xludf.DUMMYFUNCTION("IFERROR( IF(LEN(TRIM(B99))=6, DATE(2000+VALUE(RIGHT(TRIM(B99),2)),MATCH(LEFT(TRIM(B99),3),{""Jan"",""Feb"",""Mar"",""Apr"",""May"",""Jun"",""Jul"",""Aug"",""Sep"",""Oct"",""Nov"",""Dec""},0),15), IF(REGEXMATCH(TRIM(B99),""^\d{2}[/-]\d{2}[/-]\d{4}$"&"""), DATE(VALUE(RIGHT(TRIM(B99),4)),VALUE(MID(TRIM(B99),4,2)),VALUE(LEFT(TRIM(B99),2))), DATEVALUE(TRIM(B99)))), ""CHECK"")"),45407.0) -> 45407 | R99: =IF(O99="CHECK","CHECK",TEXT(O99,"mmm")) -> Apr | S99: =IF(O99="CHECK","CHECK","Q"&INT((MONTH(O99)-1)/3)+1) -> Q2 | T99: =IFERROR(IF(G99="see notes",IF(ISNUMBER(VALUE(L99)),VALUE(L99),0),IF(G99="",0,IF(H99="GBP",VALUE(G99)*1.27,IF(AND(ISNUMBER(VALUE(G99)),F99="Revenue",VALUE(G99)<0),ABS(VALUE(G99)),IF(ISNUMBER(VALUE(G99)),VALUE(G99),0))))),0) -> 27844.39
A100: TXN-1368 | B100: 27-09-2024 | C100: Expense | D100: Engineering | E100: Eng | F100: PR Agency - HubSpot | G100: 27284.9 | H100: USD | I100: HubSpot | J100: Sep | K100: Q3 | N100: =IFERROR(VLOOKUP(TRIM(E100),$P$2:$Q$23,2,FALSE),"UNMAPPED - CHECK") -> Engineering | O100: =IFERROR(__xludf.DUMMYFUNCTION("IFERROR( IF(LEN(TRIM(B100))=6, DATE(2000+VALUE(RIGHT(TRIM(B100),2)),MATCH(LEFT(TRIM(B100),3),{""Jan"",""Feb"",""Mar"",""Apr"",""May"",""Jun"",""Jul"",""Aug"",""Sep"",""Oct"",""Nov"",""Dec""},0),15), IF(REGEXMATCH(TRIM(B100),""^\d{2}[/-]\d{2}[/-]\d"&"{4}$""), DATE(VALUE(RIGHT(TRIM(B100),4)),VALUE(MID(TRIM(B100),4,2)),VALUE(LEFT(TRIM(B100),2))), DATEVALUE(TRIM(B100)))), ""CHECK"")"),45562.0) -> 45562 | R100: =IF(O100="CHECK","CHECK",TEXT(O100,"mmm")) -> Sep | S100: =IF(O100="CHECK","CHECK","Q"&INT((MONTH(O100)-1)/3)+1) -> Q3 | T100: =IFERROR(IF(G100="see notes",IF(ISNUMBER(VALUE(L100)),VALUE(L100),0),IF(G100="",0,IF(H100="GBP",VALUE(G100)*1.27,IF(AND(ISNUMBER(VALUE(G100)),F100="Revenue",VALUE(G100)<0),ABS(VALUE(G100)),IF(ISNUMBER(VALUE(G100)),VALUE(G100),0))))),0) -> 27284.9
...

Sheet Pivot Table 2

Sheet Analysis
A1: NEXORA SOFTWARE — FY2024 FINANCIAL ANALYSIS
A2: Analyst: Temmygabriel | Source: Cleaned Data sheet | All amounts in USD
A4: REVENUE SUMMARY
A5: Category | B5: Total Actual ($) | C5: Notes
A6: Subscription | B6: =SUMIFS(Cleaned_sheet!$T:$T,Cleaned_sheet!$C:$C,"Revenue",Cleaned_sheet!$D:$D,"Subscription") -> 11155691 | C6: Core ARR — 83% of total revenue
A7: Professional Services | B7: =SUMIFS(Cleaned_sheet!$T:$T,Cleaned_sheet!$C:$C,"Revenue",Cleaned_sheet!$D:$D,"Professional Services") -> 1569600 | C7: Outperformed budget every month — investigate for FY2025
A8: Licensing | B8: =SUMIFS(Cleaned_sheet!$T:$T,Cleaned_sheet!$C:$C,"Revenue",Cleaned_sheet!$D:$D,"Licensing") -> 647919.31 | C8: One-off deals — lumpy by nature
A9: Contra-Revenue | B9: =SUMIFS(Cleaned_sheet!$T:$T,Cleaned_sheet!$C:$C,"Contra-Revenue") -> -13442.93 | C9: Client refunds — minimal impact
A10: TOTAL REVENUE | B10: =SUMIFS(Cleaned_sheet!$T:$T,Cleaned_sheet!$C:$C,"Revenue")+SUMIFS(Cleaned_sheet!$T:$T,Cleaned_sheet!$C:$C,"Contra-Revenue") -> 13359768 | C10: Full year top line
A12: EXPENSE SUMMARY
A13: Department | B13: Total Actual ($) | C13: Notes
A14: Marketing | B14: =SUMIFS(Cleaned_sheet!$T:$T,Cleaned_sheet!$C:$C,"Expense",Cleaned_sheet!$N:$N,"Marketing") -> 2298600 | C14: Largest cost centre — 28% of total opex. Q3 spend spike warrants investigation
A15: Engineering | B15: =SUMIFS(Cleaned_sheet!$T:$T,Cleaned_sheet!$C:$C,"Expense",Cleaned_sheet!$N:$N,"Engineering") -> 1562600 | C15: Product development — expected for a SaaS business
A16: Cloud Infrastructure | B16: =SUMIFS(Cleaned_sheet!$T:$T,Cleaned_sheet!$C:$C,"Expense",Cleaned_sheet!$N:$N,"Cloud infrastructure") -> 1417863.7 | C16: Costs crept up every month in H2 — trend more concerning than annual total
A17: Sales | B17: =SUMIFS(Cleaned_sheet!$T:$T,Cleaned_sheet!$C:$C,"Expense",Cleaned_sheet!$N:$N,"Sales") -> 1168718.4 | C17: Sales team overhead — reasonable relative to revenue generated
A18: Customer Success | B18: =SUMIFS(Cleaned_sheet!$T:$T,Cleaned_sheet!$C:$C,"Expense",Cleaned_sheet!$N:$N,"Customer Success") -> 907500 | C18: Lean team supporting $13M revenue — efficient
A19: G&A | B19: =SUMIFS(Cleaned_sheet!$T:$T,Cleaned_sheet!$C:$C,"Expense",Cleaned_sheet!$N:$N,"G&A") -> 729721.97 | C19: Lowest cost centre — well controlled
A20: TOTAL OPEX | B20: =SUM(B14:B19) -> 8085004 | C20: Full year operating expenses
A22: NET POSITION | B22: Total Actual ($)
A23: Total Revenue | B23: =B10 -> 13359768
A24: Total OPEX | B24: =B20 -> 8085004
A25: NET INCOME | B25: =B23-B24 -> 5274763.6
A27: QUARTERLY BREAKDOWN — REVENUE vs EXPENSE
A28: Quarter | B28: Total Revenue ($) | C28: Total Expense ($) | D28: Net ($) | E28: Notes
A29: Q1 | B29: =SUMIFS(Cleaned_sheet!$T:$T,Cleaned_sheet!$C:$C,"Revenue",Cleaned_sheet!$S:$S,"Q1") -> 2860278.1 | C29: =SUMIFS(Cleaned_sheet!$T:$T,Cleaned_sheet!$C:$C,"Expense",Cleaned_sheet!$S:$S,"Q1") -> 1947438.1 | D29: =B29-C29 -> 912840 | E29: Solid start — revenue and expenses both stable
A30: Q2 | B30: =SUMIFS(Cleaned_sheet!$T:$T,Cleaned_sheet!$C:$C,"Revenue",Cleaned_sheet!$S:$S,"Q2") -> 3107888.8 | C30: =SUMIFS(Cleaned_sheet!$T:$T,Cleaned_sheet!$C:$C,"Expense",Cleaned_sheet!$S:$S,"Q2") -> 2320000.1 | D30: =B30-C30 -> 787888.76 | E30: Net dipped — expenses grew faster than revenue. Q2 pressure point.
A31: Q3 | B31: =SUMIFS(Cleaned_sheet!$T:$T,Cleaned_sheet!$C:$C,"Revenue",Cleaned_sheet!$S:$S,"Q3") -> 3290359 | C31: =SUMIFS(Cleaned_sheet!$T:$T,Cleaned_sheet!$C:$C,"Expense",Cleaned_sheet!$S:$S,"Q3") -> 2093850.4 | D31: =B31-C31 -> 1196508.6 | E31: Net recovered but Marketing spend peaked this quarter — efficiency question
A32: Q4 | B32: =SUMIFS(Cleaned_sheet!$T:$T,Cleaned_sheet!$C:$C,"Revenue",Cleaned_sheet!$S:$S,"Q4") -> 4114684.7 | C32: =SUMIFS(Cleaned_sheet!$T:$T,Cleaned_sheet!$C:$C,"Expense",Cleaned_sheet!$S:$S,"Q4") -> 1723715.5 | D32: =B32-C32 -> 2390969.2 | E32: Strongest quarter — Q4 recovery real but came late in the year
A33: FULL YEAR | B33: =SUM(B29:B32) -> 13373211 | C33: =SUM(C29:C32) -> 8085004 | D33: =B33-C33 -> 5288206.5 | E33: Full year net position
A35: MARKETING EFFICIENCY ANALYSIS — Q3 DEEP DIVE
A36: Quarter | B36: Marketing Spend ($) | C36: Notes
A37: Q1 | B37: =SUMIFS(Cleaned_sheet!$T:$T,Cleaned_sheet!$C:$C,"Expense",Cleaned_sheet!$N:$N,"Marketing",Cleaned_sheet!$S:$S,"Q1") -> 661013.88 | C37: Highest spend quarter — heavy H1 investment
A38: Q2 | B38: =SUMIFS(Cleaned_sheet!$T:$T,Cleaned_sheet!$C:$C,"Expense",Cleaned_sheet!$N:$N,"Marketing",Cleaned_sheet!$S:$S,"Q2") -> 627488.46 | C38: Spend eased slightly
A39: Q3 | B39: =SUMIFS(Cleaned_sheet!$T:$T,Cleaned_sheet!$C:$C,"Expense",Cleaned_sheet!$N:$N,"Marketing",Cleaned_sheet!$S:$S,"Q3") -> 630079.71 | C39: Marginal increase over Q2 — spend remained elevated
A40: Q4 | B40: =SUMIFS(Cleaned_sheet!$T:$T,Cleaned_sheet!$C:$C,"Expense",Cleaned_sheet!$N:$N,"Marketing",Cleaned_sheet!$S:$S,"Q4") -> 380017.95 | C40: Sharp pullback — but Q4 revenue was strongest. Efficiency question
A42: H1 Marketing Spend | B42: =B37+B38 -> 1288502.3
A43: H2 Marketing Spend | B43: =B39+B40 -> 1010097.7
A44: H1 vs H2 Difference | B44: =B42-B43 -> 278404.68

Sheet Power_BI_Export
A1: Transaction_ID | B1: Date_Raw | C1: Type | D1: Category | E1: Department_Raw | F1: Dept_Clean | G1: Date_Clean | H1: Month_Clean | I1: Quarter_Clean | J1: Amount_USD
A2: {={Cleaned_sheet!A2:A521,Cleaned_sheet!B2:B521,Cleaned_sheet!C2:C521,Cleaned_sheet!D2:D521,Cleaned_sheet!E2:E521,Cleaned_sheet!N2:N521,Cleaned_sheet!O2:O521,Cleaned_sheet!R2:R521,Cleaned_sheet!S2:S521,Cleaned_sheet!T2:T521}} -> TXN-1003 | B2: 09-01-2024 | C2: Revenue | D2: Subscription | E2: Sales Dept | F2: Sales | G2: 45300 | H2: Jan | I2: Q1 | J2: 68037.03
A3: TXN-1519 | B3: 2024-12-25 | C3: Expense | D3: Cloud Infrastructure | E3: cloud infra | F3: Cloud Infrastructure | G3: 45651 | H3: Dec | I3: Q4 | J3: 39375.28
A4: TXN-1083 | B4: 03/20/2024 | C4: Revenue | D4: Subscription | E4: Sales Dept | F4: Sales | G4: 45872 | H4: Aug | I4: Q3 | J4: 251866.75
A5: TXN-1428 | B5: October 22, 2024 | C5: Expense | D5: Cloud Infrastructure | E5: CLOUD | F5: Cloud Infrastructure | G5: 45587 | H5: Oct | I5: Q4 | J5: 22219.83
A6: TXN-1276 | B6: 03-07-2024 | C6: Expense | D6: Marketing | E6: marketing | F6: Marketing | G6: 45476 | H6: Jul | I6: Q3 | J6: 54150.77
A7: TXN-1129 | B7: April 14, 2024 | C7: Revenue | D7: Licensing | E7: sales | F7: Sales | G7: 45396 | H7: Apr | I7: Q2 | J7: 6708.47
A8: TXN-1348 | B8: 2024-09-15 | C8: Revenue | D8: Subscription | E8: sales | F8: Sales | G8: 45550 | H8: Sep | I8: Q3 | J8: 149903.37
A9: TXN-1295 | B9: 07/21/2024 | C9: Expense | D9: Cloud Infrastructure | E9: Cloud | F9: Cloud Infrastructure | G9: 45907 | H9: Sep | I9: Q3 | J9: 12717.64
A10: TXN-1170 | B10: 10-05-2024 | C10: Revenue | D10: Professional Services | E10: Sales Dept | F10: Sales | G10: 45422 | H10: May | I10: Q2 | J10: 21411.91
A11: TXN-1379 | B11: Sep-24 | C11: Expense | D11: G&A | E11: G and A | F11: G&A | G11: 45550 | H11: Sep | I11: Q3 | J11: 9918.62
A12: TXN-1131 | B12: 06/04/2024 | C12: Revenue | D12: Licensing | E12: SALES | F12: Sales | G12: 45388 | H12: Apr | I12: Q2 | J12: 6750.78
A13: TXN-1117 | B13: Mar-24 | C13: Expense | D13: Cloud Infrastructure | E13: Cloud | F13: Cloud Infrastructure | G13: 45366 | H13: Mar | I13: Q1 | J13: 16812.38
A14: TXN-1328 | B14: Aug-24 | C14: Expense | D14: Engineering | E14: Eng | F14: Engineering | G14: 45519 | H14: Aug | I14: Q3 | J14: 21612.23
... A521: TXN-1422 | B521: November 05, 2024 | C521: Expense | D521: G&A | E521: General & Admin | F521: G&A | G521: 45601 | H521: Nov | I521: Q4 | J521: 27339.38
